Workbook

Sheet Advertising
A1: ID | B1: Network URL [URL] | C1: Date of Analysis [DATE] | D1: Reviewer [Name] | E1: Date of Selling/Sharing (Buying/Collecting) Doublechecked by SZ [DATE] | F1: Crosslisted [0, 1] | G1: Crosslisted Category [Category Name] | H1: Targeted Advertising [0, 1] | I1: Evidence | J1: Profiling [0, 1] | K1: Evidence | L1: Selling/Sharing (Buying/Collecting) [0, 1] | M1: Evidence | N1: Setting: To Opt Out [0, 1] | O1: Evidence | P1: Selling By Default [0, 1] | Q1: Evidence | R1: Sign of Not Selling [0, 1] | S1: What is it [How it opts out] | T1: Evidence | U1: Relevant URLs [URL]
A2: 11 | B2: http://www.activeconversion.com/ | C2: 45237 | D2: Sophie | E2: 45529 | F2: 0 | H2: 1 | I2: We may collect information about you from other sources, including our partners, and combine this information with the Personal Information provided by you. This helps us update our records, identify new customers, create tailored advertising, and analyze overall trends so we may facilitate and provide relevant content, event promotions, and services that may be of interest to you. | J2: 1 | K2: We may collect information about you from other sources, including our partners, and combine this information with the Personal Information provided by you. This helps us update our records, identify new customers, create tailored advertising, and analyze overall trends so we may facilitate and provide relevant content, event promotions, and services that may be of interest to you. | L2: 1 | M2: We may collect information about you from other sources, including our partners, and combine this information with the Personal Information provided by you. This helps us update our records, identify new customers, create tailored advertising, and analyze overall trends so we may facilitate and provide relevant content, event promotions, and services that may be of interest to you. Our platforms rely heavily on the sharing and management of data. As such, we have worked diligently to ensure we comply with regulations across the globe including GDPR, PIPEDA, and the California Privacy Rights Act. | N2: 0 | P2: 1 | R2: 0 | U2: https://activeiq.co/privacy-data/ https://activeiq.co/privacy/
A3: 22 | B3: https://adaptmx.com/ | C3: 45227 | D3: Sophie | E3: 45529 | F3: 1 | G3: FingerprintInv | H3: 1 | I3: We use the information we collect to provide and improve Monet Engine Services, including for the following purposes: Serving ads: Allowing publishers to offer advertising inventory in their mobile apps and websites, and advertisers to bid on and fill that inventory. | J3: 1 | K3: When you interact with a website or app that uses the Monet Engine Services, we may collect information about your device and the ads you view or click. The Monet Engine Services are designed to avoid collecting information that identifies you personally, such as your name, address, or email address. | L3: 1 | M3: We share with advertiser customers information so that they can decide whether to bid on ad inventory or serve an advertisement and choose the best ad for that device. Monet Engine Customers are obligated to use the information they receive in compliance with applicable laws and regulations. ... The California Consumer Privacy Act (CCPA) requires to disclose to California residents below ... The categories of information that we “sell” or discloses to third parties ... Information as to how you can access, delete, or opt-out of the sale of your personal information. | N3: 1 | O3: Form that's a link to One Trust | P3: 1 | R3: 0 | S3: Nothing on the actual website | U3: https://adaptmx.com/privacy-policy/
A4: 59 | B4: https://adman.gr/ | C4: 45228 | D4: Oliver | E4: 45529 | F4: 0 | H4: 1 | I4: "ADMAN and GRXchange may use data it processes to limit the number of times a user sees a particular ad, to customize or personalize ads based on the context of the page or location(country) of the user, to determine the effectiveness of the ads, and for identifying fraudulent activity." | J4: 1 | K4: "ADMAN and GRXchange may use data it processes to limit the number of times a user sees a particular ad, to customize or personalize ads based on the context of the page or location(country) of the user, to determine the effectiveness of the ads, and for identifying fraudulent activity." | L4: 1 | M4: ADMAN and GRXchange may use data it processes to limit the number of times a user sees a particular ad, to customize or personalize ads based on the context of the page or location(country) of the user, to determine the effectiveness of the ads, and for identifying fraudulent activity. | N4: 1 | P4: 1 | R4: 0 | U4: https://adman.gr/privacy
A5: 71 | B5: http://www.admedia.com/ | C5: 45185 | D5: Oliver | E5: 45529 | F5: 0 | H5: 1 | I5: "These cookies collect information about your browsing habits in order to make advertising more relevant to you and your interests." | J5: 1 | K5: "At times, we may find it necessary to use personally identifiable information as a means to keep you informed of other possible products and/or services that may be available to you from www.admedia.com" | L5: 1 | M5: "Marketing or Advertising Cookies : These cookies collect information about your browsing habits in order to make advertising more relevant to you and your interests." ... Under this Privacy Policy, and by law if you are a resident of California, you have the following rights: ... The right to say no to the sale of Personal Data. You also have the right to ask AdMedia not to sell your Personal Data to third parties. You can submit such a request by visiting our "Do Not Sell My Personal Information" section or web page. | N5: 1 | O5: "opt out of the use of your personal information for interest-based advertising purposes and these potential sales as defined under CCPA law, you may do so by emailing legal@admedia.com" | P5: 1 | Q5: Proof by existence of opt out mechanism | R5: 0 | S5: Unclear, especially when done through email | U5: https://admedia.com/privacy/
A6: 88 | B6: http://www.adperfect.com/ | C6: 45230 | D6: Oliver | E6: 45529 | F6: 0 | H6: 1 | I6: "we collect and store personal information from individuals who visit our Customers’ websites and interact with our platform for purposes of creating an obituary or classified advertisement" | J6: 1 | K6: "Categories of personal information that we may collect automatically when you use the Services include" | L6: 1 | M6: AdPerfect is a software-as-a-service provider that licenses the use of its obituary and classified advertisement creation tool to newspapers (our “Customers”). As part of providing these Services, we collect and store personal information from individuals who visit our Customers’ websites and interact with our platform for purposes of creating an obituary or classified advertisement (“End Users”). ... We do not sell personal information. ... As a California resident, you have the following rights with respect to your personal information: You have the right to request to know about personal information collected, disclosed, or sold. | N6: 0 | P6: 1 | R6: 0 | U6: https://www.adperfect.com/privacy-policy
A7: 113 | B7: https://www.adtheorent.com/ | C7: 45184 | D7: Oliver | E7: 45529 | F7: 0 | H7: 1 | I7: "AdTheorent is a publicly traded (NASDAQ-listed) digital ad network and DSP which uses machine learning, data science and related technology to assist advertisers and advertising agencies in their efforts to deliver targeted and useful digital advertisements to consumers." | J7: 1 | K7: "As such, we do engage in “profiling.”" | L7: 1 | M7: AdTheorent is not a "seller" of Personal Information but AdTheorent is a downstream "user" or certain Personal Information provided by publishers. | N7: 1 | O7: any User is free to Opt-Out of any such future practice or use of User-specific behavioral, geocoding or interest-based targeted advertising by clicking here. | P7: 1 | Q7: Proof by existence of opt out mechanism | R7: 1 | S7: It places a unique cookie with your user ID that stops targeted advertising | T7: https://opt-out.adentifi.com/ | U7: https://opt-out.adentifi.com/ https://www.adtheorent.com/privacy-policy
A8: 121 | B8: http://adventive.com/ | C8: 45188 | D8: Sophie | E8: 45529 | F8: 0 | H8: 1 | I8: For example, we may combine information entered on the Adventive sales form with information received from a third-party sales integration vendor to enhance our ability to market our services to Customers or potential customers. | J8: 1 | K8: This information may include, but is not limited too, Internet Protocol (IP) addresses, system configuration information, referring URLs, locale and language settings. | L8: 0 | M8: Effective January 1, 2020, all agreement(s) entered into by and between Adventive, Inc. and You addressing our processing of Personal Information on your company’s behalf (the “Agreements”) are hereby amended to clarify Adventive as a Service Provider | N8: 1 | O8: you may opt-out by clicking here to access tools from the Network Advertising Initiative | P8: 1 | Q8: Proof by existence of optout | R8: 0 | U8: https://adventive.com/legal/privacy-policy/ https://adventive.com/legal/ccpa/ https://static.adventivecdn.com/legal/2020-01-01-Adventive-CCPA-Amendment.pdf
A9: 182 | B9: http://www.audience2media.com/ | C9: 45233 | D9: Oliver | E9: 45529 | F9: 0 | H9: 1 | I9: "We further create behavioural categories by simply identifying which websites' online users visit" | J9: 1 | K9: " create real time interests of the anonymous online user, based on their web surfing habits." | L9: 1 | M9: Audience2Media is an Audience Targeting Platform (KRYPTON) & Influencer Marketing Platform (IMPACT). Audience2Media specialises in targeting online users by displaying relevant adverts on specific websites a mobile apps. ... Publishers are websites that we source to collect user data, which allows Audience2Media to serve relevant ads to online users. | N9: 1 | P9: 1 | R9: 0 | U9: https://www.audience2media.com/privacy
A10: 184 | B10: https://audigent.com/ | C10: 45228 | D10: Sophie | E10: 45529 | F10: 0 | H10: 1 | I10: The Platform ingests information, including personal information, provided by clients, data providers, partners, and other third-party sources to allow clients to use such data to target ads and/or to leverage other Data Functions. | J10: 1 | K10: we may collect information about you and your device. While this information does not enable us to directly identify you or other users (we do not know your name or contact information), that information may be considered “personal data” or “personal information” under applicable privacy laws. | L10: 1 | M10: Right to opt out of selling or sharing. At the time this Platform Privacy Policy was last updated, we (1) SELL personal information; and (2) we SHARE personal information for the purpose of cross-context behavioral advertising. | N10: 1 | O10: To opt out of interest-based advertising on the Platform, go to Audigent’s Privacy Center. | P10: 1 | R10: 1 | S10: adgt | U10: https://audigent.com/platform-privacy-policy
A11: 205 | B11: http://beachfront.com/ | C11: 45225 | D11: Oliver | E11: 45529 | F11: 0 | H11: 1 | I11: "We utilize cookies to store user data that can aid in targeting of advertisements" | J11: 0 | L11: 1 | M11: We are not in the business of collecting, using, or selling consumer data; however we do offer technologies to advertisers and publishers that allows them to sell and purchase space or digital advertisements to try and ensure that the audience they desire sees their ads and that the advertising itself is delivered and the performance of the advertising can be analyzed. Since we share personal information collected through the Services for commercial purposes and this sharing enables BFM to generate valuable consideration, some of these categories of personal information could be deemed as “sold” in the past twelve months. | N11: 1 | P11: 1 | R11: 0 | U11: https://www.beachfront.com/privacy-policy https://www.beachfront.com/beachfront-media-llc-privacy-rights-notice
A12: 213 | B12: https://bidmind.com | C12: 45188 | D12: Sophie | E12: 45529 | F12: 0 | H12: 1 | I12: We also use User’s Advertising/Device ID and the information associated with User’s device Advertising/Device ID over time ... to enhance our services and to select Bidmind Clients’ ads that are most likely to be of interest to User. | J12: 1 | K12: Bidmind servers may receive and store an advertising identifier (“Advertising ID”) or device identifier (“Device ID”), either of them is a pseudonymous number that is associated with user of our Client | L12: 1 | M12: In some cases, based on data we collect ourselves, or receive from our Clients or data partners (e.g. Audiences as defined below), we infer within a reasonable probability that another browser or device should be associated with the same Adverting/Device ID. ... We will share the information collected about you as described above for various business purposes, with service providers and with third parties, including our Clients. The table below describes how and with whom we share or disclose personal information, and whether we believe we have sold or shared a particular category of information in the prior 12 months. | N12: 1 | O12: You can always opt-out of the serving of targeted advertising by Bidmind by clicking here. | P12: 1 | Q12: Proof by existence of optout | R12: 0 | S12: have a website to put in your information | U12: https://bidmind.com/privacy-policy/
A13: 218 | B13: http://www.bidvertiser.com/ | C13: 45213 | D13: Oliver | E13: 45529 | F13: 0 | H13: 1 | I13: "To enable advertisements delivery, including behavioral advertising" | J13: 1 | K13: "These cookies may also be used to enable third-party advertising networks to deliver ads that may be relevant to you based upon your activities or interests." | L13: 1 | M13: Get exactly the traffic you want - when you want. Geo, device, OS, browser, ISP, carrier, subid, time-of-day, channel, contextual and more. | N13: 0 | P13: 1 | R13: 0 | U13: https://www.bidvertiser.com/ https://www.bidvertiser.com/privacy/
A14: 227 | B14: https://blockthrough.com/ | C14: 45230 | D14: Oliver | E14: 45529 | F14: 0 | H14: 1 | I14: "Other cookies also enable us to track and target the interests of our users to enhance the experience on our Websites." | J14: 1 | K14: "During your visit to Blockthrough.com, we collect certain information automatically from your device" | L14: 0 | M14: When processing Personal Information on behalf of our customers, Blockthrough is acting as the “data processor” and the customer is the “data controller”. | N14: 0 | P14: 1 | R14: 0 | U14: https://blockthrough.com/privacy-policy/
A15: 228 | B15: http://www.blogher.com/ | C15: 45188 | D15: Sophie | E15: 45529 | F15: 0 | H15: 0 | J15: 1 | K15: Demographic, statistical and interest information such as interests, lifestyle information, hobbies, health and wellness information, your age, date of birth, gender, income and other personal finance information, sexual orientation, and race or ethnicity* (to the extent permitted by and in accordance with applicable law. | L15: 1 | M15: California, Colorado, Connecticut, and Virginia residents may opt out of the “sale” of their personal information or processing or sharing of your information for online targeted advertising purposes. We sell or share certain of your information to third parties that may directly provide you with offers and promotions and opportunities that may be of interest to you. | N15: 1 | O15: You may have the ability to accept or decline (or opt out of) certain cookies for analytics & targeted advertising on our Services depending on your jurisdiction. | P15: 1 | Q15: Proof by existence of optout | R15: 0 | U15: https://www.pmc.com/privacy-policy
A16: 265 | B16: https://carts.guru/ | C16: 45188 | D16: Sophie | E16: 45529 | F16: 1 | G16: FingerprintInv | H16: 1 | I16: Send Visitors information for marketing purposes (where it is in accordance with Visitors’ communication preferences); | J16: 1 | K16: We may ask Visitors to provide specific information set out in an online inquiry form (for example, name, contact details, company name, country, monthly visitors volume, billing information, profile information etc). | L16: 1 | M16: We may also share personal information collected through the Services with third party companies so that they may offer products and services that We believe will be of interest to You. We may also share personal information with third party advertising-serving companies to better target the adverts and other content displayed on Our site and to provide offers We think may be of interest to You. You may opt-out of disclosure of Your information to third parties for direct marketing purposes – see the Choice and Opt-Out section below. ... California law provides that California residents have a right to request that businesses tell them how their personally identifiable information has been shared with third parties for those third parties’ direct marketing purposes. However, there is an exception to this requirement for businesses that have adopted and disclosed, in their privacy policy, a policy of not disclosing a person’s personally identifiable information to third parties for those third parties’ direct marketing purposes if that person has exercised an option to opt-out of the disclosure of their personally identifiable information to third parties for such purposes. Carts Guru has adopted a policy of allowing You to opt-out of the disclosure of Your personally identifiable information to third parties for their direct marketing purposes and thus falls within this exception. Instructions for opting out can be found in the section entitled found in the Choice and Opt-Out section above. | N16: 1 | O16: You may opt-out of disclosure of Your information to third parties for direct marketing purposes | P16: 1 | Q16: Proof by existence of optout | R16: 0 | T16: However, if You want to contact Us directly about accessing, changing or deleting Your personal information, or altering Your data or marketing preferences, please email Us at privacy@carts.guru. | U16: https://www.carts.guru/privacy-policy/services-privacy-policy
A17: 295 | B17: https://www.clixtell.com/ | C17: 45233 | D17: Sophie | E17: 45529 | F17: 1 | G17: FingerprintInv | H17: 1 | I17: Improve and develop the services and content offered (including by matching them to the user on the basis of his identity); | J17: 1 | K17: Some of this data can be considered as Personal Data such as your name, IP address, email etc. All Personal Data will be stored securely and only used when necessary such as to log into your account or provide customer support | L17: 1 | M17: Clixtell’s call tracking software reveals which keywords, campaigns, and ads drive into calls and conversions. Measure all phone calls from all your marketing channels, online & offline. Watch and record your customer’s full journey from search to click and call. | N17: 0 | P17: 1 | R17: 0 | U17: https://www.clixtell.com/ https://www.clixtell.com/privacy-policy/
A18: 328 | B18: https://www.crimtan.com/ | C18: 45188 | D18: Sophie | E18: 45529 | F18: 0 | H18: 1 | I18: We will only use ID-related Data in ways that the law allows us to. Most commonly, we will use ID-related Data in the following circumstances: To provide Relevant Advertising that you have consented to receive | J18: 1 | K18: We also collect, use and share Aggregated Data such as statistical or demographic data for any purpose. Aggregated Data may be derived from ID-related Data but is not associated with an ID, and thus is not treated as personal data in law. | L18: 1 | M18: Once you consent to Relevant Advertising, when you visit the sites of our advertiser clients or sites where we serve online advertising, we associate what we learn about your visit with the ID. Here is how this works: | N18: 1 | O18: You may withdraw this consent at any time by using the button below, through a Consent Management Platform, by completing the Data Subject Request Form or by emailing dpo@crimtan.com | P18: 1 | Q18: Proof by existence of optout | R18: 0 | S18: must go through contact to get permission to opt out | U18: https://www.crimtan.com/privacy-policy/
A19: 340 | B19: http://www.datranmedia.com/ | C19: 45188 | D19: Sophie | E19: 45529 | F19: 0 | H19: 1 | I19: PulsePoint operates advertising technology, and as such, has many partners in the ad tech ecosystem that it works with in order to provide advertisements to end users of websites, Apps, and other various advertising platforms and media. | J19: 1 | K19: Personally identifiable information (“PII”) is information unique to you that may be used to directly identify you individually. We may acquire PII from our publishers, advertising partners, or other third parties, but only where we have contractually required that these third parties have obtained your consent or are otherwise legally permitted or required to disclose your PII to us | L19: 1 | M19: The CCPA defines “sale” broadly, and it may include our sharing information that we have about you, such as a cookie ID or IP address, with third party advertising partners who may use this information, on our behalf, to help us deliver advertising on the WebMD Sites as well as on third party websites. You have the right to opt- out of the sale or share of your personal information subject to certain exclusions as described below. Once we receive your request, we will not sell or share your personal information, unless an exclusion applies. We may request that you authorize the sale or sharing of your personal information after 12 months following your opt-out. | N19: 1 | O19: You have various options to opt out of our Platform for IBA/OBA. Opting out does not prevent you from seeing ads; it simply means that we will no longer collect data for the purpose of IBA/OBA | P19: 1 | Q19: Proof by existence of optout | R19: 1 | S19: Cookie name not identified | T19: The DAA and NAI opt-out tools are cookie-based. It signals your preferences to us so that we do not collect data online or deliver ads for the purpose of IBA/OBA. | U19: https://www.pulsepoint.com/legal/platform-privacy-policy#info_we_share
A20: 341 | B20: http://datonics.com/ | C20: 45233 | D20: Oliver | E20: 45529 | F20: 0 | H20: 1 | I20: "Based on this data, we may then display targeted advertisements across devices that we believe are associated" | J20: 1 | K20: "We may use your information to match it with other public and private data sources in order to enhance our records, such as appending additional information to your profile, " | L20: 1 | M20: We share the information we collect with our advertising partners so they may deliver relevant online advertisements to users. Personal Information Sales Opt-Out and Opt-In Rights. You have the right to direct us to not sell your personal information at any time (the "right to opt-out"). To exercise your right to opt-out, click here. | N20: 1 | P20: 1 | R20: 0 | U20: https://www.datonics.com/technology-privacy-policy
A21: 348 | B21: http://delivr.com/ | C21: 45233 | D21: Oliver | E21: 45529 | F21: 0 | H21: 1 | I21: "The legal basis for this use and other processing will include (as relevant): to provide you with relevant marketing communications;" | J21: 0 | L21: 0 | M21: In this context, if you are subject to CCPA, you are a Business and Delivr is your Service Provider. Your sharing of Personal Information related to your end users with Delivr, and Delivr’s collection of Personal Information related to your end users, are done to facilitate Delivr’s performance of its services that you contracted for. ... Delivr does not receive from you, and you do not pay Delivr, any monetary or other valuable consideration for making Personal Information available to Delivr. | N21: 0 | P21: 1 | R21: 0 | U21: https://delivr.com/page/710/california-consumer-privacy-act-ccpa-notice https://delivr.com/page/511/privacy-notice
A22: 362 | B22: http://www.directresponsegroup.com/ | C22: 45228 | D22: Sophie | E22: 45529 | F22: 0 | H22: 1 | I22: We use Personally Identifiable Information to customize the Site, to make appropriate service offerings | J22: 1 | K22: We may collect basic user profile information from all of our Visitors. We collect the following additional information from our Authorized Customers: the names, addresses, phone numbers and email addresses of Authorized Customers, the nature and size of the business, and the nature and size of the advertising inventory that the Authorized Customer intends to purchase or sell. | L22: 1 | M22: Personally Identifiable Information about Authorized Customers may be shared with other Authorized Customers who wish to evaluate potential transactions with other Authorized Customers. We may share aggregated information about our Visitors, including the demographics of our Visitors and Authorized Customers, with our affiliated agencies and third party vendors. We also offer the opportunity to "opt out" of receiving information or being contacted by us or by any agency acting on our behalf. | N22: 0 | O22: Visitors and Authorized Customers may opt out of receiving unsolicited information from or being contacted by us and/or our vendors and affiliated agencies by responding to emails as instructed, or by contacting us at 201 Old Country Road, Suite 204, Melville, NY 11747 | P22: 1 | R22: 0 | U22: https://www.directresponsegroup.com/privacy-policy/
A23: 368 | B23: http://doublepimp.com/ | C23: 45186 | D23: Oliver | E23: 45529 | F23: 0 | H23: 1 | I23: "Ad targeting: Cookies may be used to display relevant advertisements to visitors." | J23: 0 | L23: 1 | M23: Partner ad networks: we may share a portion of your personal data (i.e. IP address and User Agent) with other third-party ad networks or business partners who are interested in serving End-Users advertisements from their own advertisers. ... Under CCPA’s broad definition, “personal information” may also include (in addition to names, addresses, and the like) unique identifiers, IP addresses, and even inferences which may be drawn from any of the above. CCPA also defines the term “sell” broadly. Its meaning includes “renting, releasing, disclosing, disseminating, making available, [and] transferring…for monetary or other valuable consideration.” Under these broad definitions, certain transfers of information (such as IP addresses, User Agents, and combinations of these) which are necessary to operate our network could arguably be deemed a “sale” of “personal information” under CCPA. You have the right to opt out of this “sale.” For more information on how to opt out, click here. | N23: 1 | O23: You have the right to opt-out from targeted advertising. In such case, Advertisers will not be able to customize their ads based on certain behaviors or audience type and your data will not be shared with third-party ad networks. If you would like to do so, you can send us an email to dpo@twinred.com and our Support Team will redirect you to a privacy center page where you can confirm your choice. | P23: 1 | Q23: Proof by existence of optout | R23: 0 | U23: https://doublepimp.com/privacypolicy#h_2350869264351608142954940
A24: 372 | B24: https://www.drift.com/ | C24: 45215 | D24: Oliver | E24: 45529 | F24: 1 | G24: Analytics | H24: 0 | J24: 1 | K24: "we collect certain information automatically, including the type of mobile device you use, your mobile device’s unique device ID, the IP address of your mobile device, your mobile operating system, the type of mobile Internet browser you use, and your general location information as described further below." | L24: 1 | M24: In the past twelve (12) months, Drift has collected from individuals, and may have shared or sold (as defined in the CCPA), certain categories of Personal Information (as defined in the CCPA) as follows: | N24: 1 | O24: "Do Not Sell My Personal Information: https://preferences.drift.com/dont_sell" | P24: 1 | R24: 0 | S24: unclear | U24: https://www.drift.com/privacy-policy/
A25: 378 | B25: http://www.ebay.com/ | C25: 45228 | D25: Sophie | E25: 45529 | F25: 1 | G25: EmailAgg | H25: 1 | I25: On this basis, we process your data for the following purposes: Customization of page content to display the items and services you may like based on the actions you take. | J25: 1 | K25: Data about your activities and interactions with our advertising partners including data about the advertisements you were shown, how often they were shown, when and where they were shown, and whether you took any action, such as clicking on an advertisement or making a purchase. The user segment or category into which you as a user fall, for example: female, 20-49 years old, interested in sneakers. | L25: 1 | M25: We share and sell personal information under California Privacy Laws. The following Table 3.1 lists the categories of personal information that are “shared” or “sold”, and the categories of recipients who receive this information. | N25: 1 | O25: AdChoices Page | P25: 1 | R25: 1 | S25: Switch | U25: https://www.ebayinc.com/company/privacy-center/privacy-notice/state-privacy-disclosures/#california
A26: 399 | B26: http://www.etrigue.com/ | C26: 45237 | D26: Sophie | E26: 45660 | F26: 0 | H26: 1 | I26: has GDPR | J26: 1 | K26: Before we collect any personally identifiable information, we will provide an explanation for the possible use of the data. The information supplied will be used by eTrigue Corporation to respond to inquiries, supply requested information on eTrigue Corporation products and services, or track orders placed with eTrigue Corporation. | L26: 1 | M26: Authorized third parties may be utilized by eTrigue Corporation to collect, track and process such information. | N26: 0 | O26: link in emails, not available on page | P26: 1 | R26: 0 | U26: https://www.etrigue.com/trust/privacy-policy/
A27: 411 | B27: http://expo-max.com/ | C27: 45233 | D27: Oliver | E27: 45660 | F27: 0 | H27: 1 | I27: "Deliver customized content and advertising that may be of interest to you;" | J27: 1 | K27: "We collect information in the following ways: Automatically when you visit our web sites or use our products and services." | L27: 1 | M27: We collect information in the following ways: ... Via advertisement serving and tracking codes that you install on your website; Automatically when you visit our web sites or use our products and services. We use "cookies" (small files placed on your hard drive) on most of our pages to help analyze our web page flow, content and advertising, promotional effectiveness, as well as security. ... We use the information we collect in a variety of ways, including to: ... Deliver customized content and advertising that may be of interest to you; ... | N27: 0 | P27: 1 | R27: 0 | U27: http://expo-max.com/privacy/
A28: 423 | B28: https://www.nexstardigital.com/ | C28: 45233 | D28: Oliver | E28: 45660 | F28: 0 | H28: 1 | I28: " We may use Personal Information collected directly during the registration process and/or via cookies, web beacons, and other similar technologies to help us evaluate and modify existing services and features, as well as provide certain information to third parties to provide advertising that is targeted to you." | J28: 1 | K28: "We may also automatically collect information that does not directly identify you but may be considered your personal data under applicable law (“Other Information”)." | L28: 1 | M28: We do not sell your Identifiable Information without your consent. However, we do share certain Personal Information with some of our partners which may be considered a “sale” under the California Consumer Privacy Act (“CCPA”) and other similar privacy laws (collectively, “Privacy Laws”), therefore, when required by applicable Privacy Laws, we give residents the right to opt out of the sale of your Personal Information (“Opt-Out Right”). | N28: 1 | P28: 1 | R28: 0 | U28: https://www.nexstar.tv/privacy-policy/
A29: 427 | B29: http://www.flashtalking.com/ | C29: 45237 | D29: Sophie | E29: 45660 | F29: 1 | G29: Analytics | H29: 1 | I29: This helps indicate if an ad is effective for the advertiser, and helps the advertiser tailor messages, offers, recommendations, and promoted content to your preferences over time. | J29: 1 | K29: we automatically collect certain information when you access websites that incorporate our Services or otherwise interact with our Services. This information does not identify you individually, but it does reflect information about the websites and mobile apps you visit and use and how you interact with the ads we serve. | L29: 1 | M29: Flashtalking’s platform uses various technologies to collect information, including cookies, web beacons, web storage, advertising device identifiers, and similar technologies. Cookies are small data files stored on your hard drive or in device memory that help to recognize that the same device has been seen before, and where, in the context of a client’s ad campaign. This helps indicate if an ad is effective for the advertiser, and helps the advertiser tailor messages, offers, recommendations, and promoted content to your preferences over time. ... We may disclose the information we collect as follows or as otherwise described in this Privacy Policy: With our advertising and publishing clients, with respect to the performance of their online ads; ... Your choices Opting out of interest-based advertising and collection of personal information Please visit our Opt Out Page. ... California consumer disclosure and rights (CCPA/CPRA) ... Categories of Personal Information we sell We do not sell personal information. Categories of Third Parties to whom Personal Information is sold We do not sell personal information. Categories of third parties to whom information was shared for a business purpose We do not share personal information with third parties except as directed by a client on their behalf. | N29: 1 | O29: Link to opt out page | P29: 1 | R29: 0 | S29: ftcOpt | T29: it doesn't work in the console | U29: https://www.flashtalking.com/privacypolicy
A30: 439 | B30: http://www.freedom.com/ | C30: 45223 | D30: Sophie | E30: 45660 | F30: 0 | H30: 1 | I30: We may use the information that we collect from you to: ... Send you information about products or services that we think may be of interest to you; | J30: 1 | K30: We may also collect personal information about you from the following categories of sources: advertising networks, internet service providers, data analytics providers, government entities, operating systems and platforms, social networks, and data brokers. | L30: 1 | M30: Third party advertisers, including Google, may also use cookies to collect non-personally identifiable information from your browser, such as pages you visited, tools you have interacted with, the channel or method in which you arrived on our Site, etc., so that they can tailor the ads you see to your preferences and behaviors. Third party cookies may also track the number of ad impressions, other uses of ad services, and interactions with these ads. | N30: 1 | O30: To learn more about this online advertising or to opt-out of this type of advertising, please click on the following links: | P30: 1 | R30: 0 | U30: https://www.freedommortgage.com/disclosures/privacy-policy
A31: 458 | B31: https://www.geoedge.com/ | C31: 45225 | D31: Oliver | E31: 45660 | F31: 0 | H31: 1 | I31: "We use cookies and similar technologies to help personalize your experience by helping save your settings and customizations across visits and providing you targeted content and advertisements matching your interests" | J31: 1 | K31: "When you use the App and/or Site, certain information may be automatically gathered about your computer or mobile device, such as operating system, IP address, device ID, and subject to your consent as may be required under applicable law, (geo) location, as well as your browsing history and any information regarding your viewing and purchase history on our App and/or Platform." | L31: 1 | M31: We may disclose information, including Personal Data we collect from and/or about you, to our trusted service providers, business partners, affiliates, subcontractors, who may use such information to ... (3) subject to your consent as may be required under applicable law, provide to you targeted offers and advertising on both our App and/or Site, as well as on other apps, platform and sites you choose to visit. | N31: 0 | P31: 1 | R31: 0 | U31: https://www.geoedge.com/privacy-policy/
A32: 459 | B32: http://getintent.com/ | C32: 45222 | D32: Sophie | E32: 45660 | F32: 0 | H32: 1 | I32: Each bid request contains the description of the interests of the audience that is likely to see the advertisement. The Platform compares the description of the audience under the bid request with the parameters of the Client’s advertising campaign. | J32: 1 | K32: When our Clients use the Platform, they may also use their data received from other sources (not from GetIntent) and other data that identifies the Client that is collected as a result of or generated by the Client’s use of the Platform (Client Data). | L32: 1 | M32: When the Sites send to the Platform bid requests (as explained in section What we do above), these bid requests may include some information about you including IP address, unique device identifiers, and the latitude and longitude of your device when you view a Site or use an App. ... We use the data processed by the Platform for the purposes of providing the Services to the Clients, in particular to analyse and report on advertising performance: the data processed is attributed to each certain advertising campaign of the Client, so the Client can monitor the performance of its advertising campaign; to improve online advertising experience and efficiency: our Platform helps the Clients to decide which advertisement to show or whether to show it and to display the Client’s particular products in response to users’ interest; to limit advertising exposure for consumers and facilitate more relevant advertising: for this purpose, we use Cross-Device IDs; | N32: 1 | O32: To opt-out or opt-in please visit the following pages: adhigh.net, digitmate.bid, cpagen.win. | P32: 1 | R32: 1 | S32: ‘Opt-out Cookie’ | T32: The Cookie previously set your browser is deleted and replaced with the Platform ‘Opt-out Cookie’ indicating your ‘opt-out’ only. | U32: https://getintent.com/privacy/
A33: 462 | B33: https://gleam.io/ | C33: 45228 | D33: Sophie | E33: 45660 | F33: 1 | G33: FingerprintInv | H33: 1 | I33: Gleam may collect and use User's personal information for the following purposes: To improve Gleam to ensure that content is presented in the most effective manner for you and for your Device; | J33: 0 | K33: Gleam also does not collect retain or share end user information including IP addresses, unique user identifiers, or personally identifiable information gathered on sites or apps not owned by Gleam, except for the limited purpose of determining conversion rates & detecting fraud | L33: 1 | M33: Gleam offers a number of integrations with 3rd party service providers that enable Campaign Owners to send Campaign Users data from Gleam for processing: ... Sailthru ... | N33: 0 | P33: 0 | R33: 0 | U33: https://gleam.io/privacy
A34: 505 | B34: https://www.indexexchange.com/ | D34: Sophie | E34: 45660 | F34: 0 | H34: 1 | I34: device advertising IDs: unique identifiers used for advertising purposes on various devices, including mobile devices | J34: 1 | K34: The information we receive is predominantly determined by each Publisher that you interact with. We are not able to determine your name, email address, or other similarly identifying information based on the Personal Data we Process | L34: 1 | M34: We may disclose, share, or sell (collectively, Share) your Personal Data with the following partners for the purpose of delivering ads to you: Buyers: we Share your Personal Data with Buyers to source ads that may be relevant to your interest(s). | N34: 1 | O34: Opt Out link | P34: 1 | Q34: Proof by existence of opt out | R34: 1 | S34: https://optout.networkadvertising.org/?c=1 | U34: https://www.indexexchange.com/privacy/exchange-platform-privacy-policy/
A35: 507 | B35: https://www.infinity.co | C35: 45186 | D35: Oliver | E35: 45660 | F35: 0 | H35: 0 | J35: 0 | L35: 1 | M35: Infinity is an analytics provider whose software allows website owners to understand the usability of their websites and the effectiveness of their marketing (the “Services”). ... 4. Disclosure of your personal data ... We may share your personal data with: our suppliers and service providers who we use in connection with and for the purposes of providing the Services, including for example providers of cloud storage, data centres and telecommunication providers. ... In order to satisfy the California Consumer Privacy Act (“CCPA”) and other relevant legislation, we are required to provide specific information for residents of California. You should also refer to the rest of this policy, which provides the requisite detail concerning: ... where we disclose this information to third parties (see Disclosure of your information). In the preceding twelve months, we have not sold any personal information belonging to consumers. ... Cookies are small data files placed on your computer by the websites you visit and can be used to help recognise you when you return to a website. We, or third party service providers, may use cookies to, among other things, measure activity, personalise your experience, remember your viewing preferences, or track your login status when accessing our site. For some of these purposes, our cookies may be tied to personal data. | N35: 0 | O35: Not needed | P35: 0 | R35: 0 | T35: Is a call analysis site, does not deal greatly with advertising | U35: https://www.infinity.co/us/privacy-policy
A36: 513 | B36: http://www.infolinks.com/ | C36: 45230 | D36: Oliver | E36: 45660 | F36: 1 | G36: FingerprintGen | H36: 1 | I36: "Serving Ads: To allow Publisher Clients to offer advertising inventory in their Digital Properties and Media Buyers to bid on and fill that inventory with relevant ads." | J36: 1 | K36: "We use cookies and other similar tracking technologies (such as pixel tags and web or browser caches) to collect information automatically from End Users’ devices." | L36: 1 | M36: When End Users visit a Digital Property that uses our technology, we (and our partners or vendors) use and deploy tracking technologies like cookies to automatically collect certain information about the End Users and their devices. Some of this information (including, for example, unique identifiers stored in a cookie or mobile advertising IDs) may identify a computer or device and may be “personal data” in some jurisdictions, including the EU. | N36: 0 | P36: 1 | R36: 0 | U36: https://www.infolinks.com/privacy-policy/
A37: 527 | B37: http://www.interpolls.com/ | C37: 45237 | D37: Sophie | E37: 45660 | F37: 0 | H37: 1 | I37: Interpolls provides Advertisers, Agencies, Publishers and its Agents the tools and services to create and deliver advertisements (also referred to as ad-serving) that you may encounter on certain web sites, monitor the performance of those advertisements, manage ad creatives for campaigns, and deliver advertisements that most likely will be relevant and interest you. | J37: 1 | K37: When Users interact with ads generated using the Interpolls Services, we may collect information on behalf of Interpolls’ Clients. Interpolls provides promotion tools and services for clients to create, manage and deliver sweepstakes or contests to users for a chance to win or earn prizes. | L37: 0 | M37: Interpolls provides Advertisers, Agencies, Publishers and its Agents the tools and services to create and deliver advertisements (also referred to as ad-serving) that you may encounter on certain web sites, monitor the performance of those advertisements, manage ad creatives for campaigns, and deliver advertisements that most likely will be relevant and interest you. ... Interpolls is a service provider as defined by CCPA. ... Interpolls has never sold any personal information of consumers. | N37: 1 | O37: Link | P37: 1 | R37: 1 | S37: optout | U37: https://www.interpolls.com/privacy
A38: 534 | B38: http://www.iprom.si/ | C38: 45188 | D38: Sophie | E38: 45660 | F38: 0 | H38: 1 | I38: The contractual processors working with the Provider are: • E-mail messaging providers (e.g. Mailchimp and others) • Providers of online advertising solutions (e.g. Google, Facebook) | J38: 1 | K38: In accordance with the purposes defined in this Privacy Policy, the Provider collects the following personal data: • Basic user information (name and surname, address) | L38: 1 | M38: In addition, cookies can be used to serve more appropriate ads and to measure ad effectiveness. The use of cookies can help us to store information for advertising purposes, including targeted, retargeting, tailored advertising, delivery of ads and clicks and conversions based on the shown ads. | N38: 1 | O38: You can opt out from collecting and using non-personal data with managing cookies in your browser or on your device. | P38: 1 | Q38: Proof by existence of optout | R38: 0 | S38: Seems to say any cookie should be blocked, but no specific cookie is mentioned | U38: https://iprom.eu/files/2022/05/iPROM-Privacy_Policy_GDPR.pdf
A39: 540 | B39: https://www.ispot.tv/ | C39: 45237 | D39: Sophie | E39: 45660 | F39: 0 | H39: 1 | I39: We collect the categories of personal information described above for the following business or commercial purposes: providing our products and services personalizing customer experience | J39: 1 | K39: See the chart below for the categories of personal information we have collected over the preceding 12 months, the retention period for each category, and the categories of sources of the information. | L39: 1 | M39: Categories of Third Parties to Whom Information is Sold or Shared - By Category: ... advertising networks, internet service providers ... Company name sells or shares personal information to third parties. You have the right at any time to direct us not to sell or share your personal information to third parties (this right is referred to as the "Right to Opt‐out."). In addition to using the "Do Not Sell My Personal Information," link on our website or here in our privacy policy link to "Do Not Sell" form, you may submit a request to exercise your Right to Opt-out as follows: ... | N39: 0 | O39: must manually contact | P39: 1 | R39: 0
A40: 544 | B40: https://www.jellyfish.com/ | C40: 45188 | D40: Sophie | E40: 45660 | F40: 0 | H40: 1 | I40: We use this information where we have a legitimate business interest to do, for example: to get in touch with you following a request you made using a form on this website; to provide our products and services; to send you marketing emails about our services, events, or other information which we think you may find interesting. | J40: 1 | K40: Information we collect about your use of the website: Technical information (including your IP address and information related to your browser and/or device) | L40: 1 | M40: As discussed above, we provide personal information to third-party advertising providers for targeted advertising purposes, so that we can provide you with more relevant and tailored ads regarding our services, or use related advertising analytics partners to understand the effectiveness of our online ads. The disclosure of your personal information to these third parties to assist us in providing these services may be considered a “sale” of personal information or the processing/sharing of personal information for targeted advertising purposes under applicable law. | N40: 1 | O40: please use the "Do Not Sell or Share My Personal Information" link in our website footer, and follow the directions provided therein. You can also submit a request to opt out of our offline disclosures of information that are subject to applicable opt out rights by emailing us at dataprotection@jellyfish.com. | P40: 1 | Q40: Proof by existence of optout | R40: 0 | S40: must go through contact to get permission to opt out | U40: https://www.jellyfish.com/en-us/privacy-policy/ https://info.jellyfish.com/en-us/ccpa-us
A41: 559 | B41: https://keywee.co | C41: 45186 | D41: Oliver | E41: 45660 | F41: 0 | H41: 1 | I41: "We may use cookies to help us understand how our services are being used, to tailor how we distribute content, and to report on delivery on the content." | J41: 1 | K41: "When you interact with the Site, we may collect information that, alone or in combination with other information, could be used to identify you (“Personal Data”)" | L41: 1 | M41: The following section of this Privacy Policy only applies to California residents. The California Consumer Privacy Act (the “CCPA”) grants users of our Site that are California residents certain rights in regards to our collection of personal information. These rights include: ... The right to opt-out of the sale of their personal information. ... Through our Site, you can choose to access certain social media websites and services that are owned and/or controlled by third parties, such as Facebook, Twitter, Instagram, Pinterest and YouTube (“Social Media Services”). When you choose to access and use Social Media Services, including interacting with our pages on those sites, you will be sharing your Personal Data and other information with them. | N41: 0 | O41: "In the event that Keywee begins selling personal information, this Privacy Policy will be updated to reflect that sale and you will be notified of such update. Additionally, you will be provided the ability to opt-out of the sale of your personal information collected by Keywee by clicking a DO NOT SELL MY PERSONAL INFORMATION link." | P41: 1 | R41: 0 | U41: https://keywee.co/privacy-policy/
A42: 607 | B42: http://www.madisonlogic.com/ | C42: 45228 | D42: Oliver | E42: 45660 | F42: 0 | H42: 1 | I42: "for example through notifications about special offers and promotions or other relevant content delivered through targeted advertising." | J42: 1 | K42: "Madison Logic may use a variety of technologies, including “cookies” that automatically or passively collect information from your computer" | L42: 1 | M42: You have the right to direct us not to sell your personal information or share it for the purposes of cross-context behavioral advertising (“opt-out’). | N42: 1 | P42: 1 | R42: 0 | U42: https://www.madisonlogic.com/privacy/
A43: 616 | B43: https://www.mashero.com/ | C43: 45186 | D43: Oliver | E43: 45660 | F43: N/A | G43: N/A | H43: N/A | I43: No privacy policy | J43: N/A | K43: No privacy policy | L43: N/A | M43: No privacy policy | N43: N/A | O43: No privacy policy | P43: N/A | Q43: No privacy policy | R43: N/A | S43: No privacy policy | T43: No privacy policy | U43: N/A
A44: 638 | B44: https://www.merkleinc.com/ | C44: 45215 | D44: Oliver | E44: 45660 | F44: 1 | G44: Analytics | H44: 1 | I44: "You have the right to request that we not include your data for any targeted advertising we conduct." | J44: 1 | K44: "You have the right to request that we not process your information for profiling." | L44: 1 | M44: You can request that we not sell or share your personal data that we have in our products by clicking Do Not Sell/Share My Info. | N44: 1 | P44: 1 | R44: 1 | S44: opt_out: OPT_OUT | U44: https://www.merkle.com/content/merkle/en/privacy-policy/united-states.html
A45: 644 | B45: https://www.minutemedia.com/ | C45: 45228 | D45: Sophie | E45: 45660 | F45: 0 | H45: 1 | I45: Marketing and Advertising; We may use Tracking Technologies (which may collect Personal Data) in order to provide you with personalized advertisements when you visit our Services. | J45: 1 | K45: The type of information collected may be influenced by the nature of our Website conducting the Activity. Such information may include your full name, information regarding your marital/relationship status and number of children, gender, year of birth, your state and city of residency, employment status, your astrological sign, and any additional information you choose to provide in connection to such Activity. | L45: 1 | M45: If we sell your Personal Data, you have the right to submit a request to opt-out of the sale of your Personal Data. You may change your decision at any time and permit us to sell your Personal Data. If you do not want us to sell your Personal Data to third parties, please click on the “Do Not Sell My Personal Information” link located on the homepages of our Brand Websites for residents located in California. | N45: 1 | O45: You may choose not to receive our promotional or marketing emails by clicking on the “unsubscribe” link in the emails that you receive from us, or contact our DPO at dpo@minutemedia.com (kindly specify the name of the relevant product from which you wish to unsubscribe from) | P45: 1 | R45: 0 | U45: https://www.minutemedia.com/policies/privacy-policy
A46: 650 | B46: http://www.mobfox.com/ | C46: 45215 | D46: Oliver | E46: 45660 | F46: 1 | G46: FingerprintingInv | H46: 1 | I46: "Targeting Cookies: for providing advertising agencies with information about your visit so that they can show you relevant adverts online." | J46: 1 | K46: "We use and deploy digital identifiers to automatically collect certain information. Some of this information may identify a particular computer or device and may be considered Personal Information." | L46: 1 | M46: "Our use of such Personal Information may qualify as a “Sale” under the CCPA, since the data we provide to third parties, including to our clients and partners might help us to generate valuable consideration. " | N46: 1 | O46: "If you wish to opt out of the use of your Personal Information for interest-based advertising purposes, you may do so by contacting us at: PrivacyCompliance@mobfox.com" | P46: 1 | R46: 0 | U46: https://www.mobfox.com/mobfox-legal https://www.mobfox.com/cookies-policy
A47: 651 | B47: http://mobilestorm.com/ | C47: 45227 | D47: Sophie | E47: 45660 | F47: 0 | H47: 1 | I47: We use this information to meet legal or regulatory requirements, to measure the use of our sites; to improve the content of our sites, and to provide tailored advertisements. | J47: 1 | K47: Categories of information. Mobilestorm processes three broad types of information: (1) Customer Account Data; (2) End User Usage Data; and (3) Customer Content. “Customer Account Data” is the personal information of a customer or potential customer of Mobilestorm. “End User Usage Data” is the personal information of end users who interact with an application that has been built on or which interacts with Mobilestorm’s platform | L47: 1 | M47: In addition to the rights outlined above, where the California Consumer Privacy Act or related data protection laws apply, you may: ... Request certain information regarding, and/or opt-out of, our disclosure of your personal information to third parties. ... If you are a California resident, to the extent that we sell your personal information to third parties, you have the right to opt out of such sale. | N47: 0 | O47: Have to email | P47: 1 | R47: 0 | U47: https://mobilestorm.com/privacy-policy/
A48: 670 | B48: http://www.mythings.com/ | C48: 45188 | D48: Sophie | E48: 45660 | F48: 0 | H48: 1 | I48: We use Facebook Pixels to register your visit on mythings.com so that we can advertise to you through Facebook’s network. Several sites use this cookie to allow Facebook to show you ads that are relevant to you and your past search history. | J48: 1 | K48: Information about your usage of the website, in terms of browser settings, IP address, and which subpages that are visited. If contact forms of newsletter form are being used, your name, company and e-mail address is stored. | L48: 1 | M48: Facebook Pixels: We use Facebook Pixels to register your visit on mythings.com so that we can advertise to you through Facebook’s network. | N48: 0 | O48: Browsers are set to accept cookies. If you prefer not to, you can set your browser to reject cookies, or to reject third-party cookies. | P48: 0 | R48: 0 | U48: https://www.mythings.com/privacy-policy/
A49: 695 | B49: https://www.createwithnova.com/ | C49: 45223 | D49: Sophie | E49: 45660 | F49: 0 | H49: 1 | I49: We use the information we collect to: ... Tailor services based on your habits and preferences. | J49: 1 | K49: We and our partners use various technologies to collect and store information when you visit, and this may include using cookies, web storage, or similar technologies to identify your browser or device. | L49: 1 | M49: Below are direct links to standards, laws, and/or regulations that are applicable to our privacy and data policies: ... (CCPA) California Consumer Privacy Act ... We may receive information about you and your activities from third-party partners, such as information from a partner when we jointly offer services or from an advertiser about your experiences or interactions with them. This information is only used in conjunction with our services for purposes that the third-party outlined with you when they collected it. ... We and our partners use various technologies to collect and store information when you visit, and this may include using cookies, web storage, or similar technologies to identify your browser or device. | N49: 0 | O49: Says they will respect it if it's one of their advertisers but doesn't give a setting | P49: 1 | R49: 0 | S49: Must be specific to advertiser | U49: https://www.createwithnova.com/privacy
A50: 709 | B50: https://onesignal.com | C50: 45223 | D50: Sophie | E50: 45660 | F50: 0 | H50: 1 | I50: To enable clients to create inferences about End Users categorized into “Data Segments”. For instance, if SDK Information indicates that a particular device is frequently seen at restaurants, we might categorize a user for targeting of local restaurant offers. Or, if a user is frequently seen at sports stadiums, we might categorize the user as a “Sports Fan.” | J50: 1 | K50: Sometimes, the SDK Information may be used to resolve identities across multiple devices, such as to match IP addresses or hashed emails to link an End User across (for instance) browsers, mobile devices, tablets, set top boxes, or other devices. | L50: 0 | M50: OneSignal is a customer engagement platform for companies around the world to enable relationships for them and their customers. This is primarily done by leveraging first party data to personalize and automate messaging through first party channels, such as email, SMS, mobile push notifications, web push notifications, and in-app messaging. OneSignal collects this first party data through a software development kit (“SDKs”) that companies use in their mobile applications and websites. These web and mobile SDKs permit app developers and websites to send, manage, optimize and customize messages to their users. ... OneSignal is the data controller for processing of certain Personal Data, such as the Personal Data of our client business contacts or the OneSignal Website Information. However, we act as a data processor (or service provider) in relation to the Services we provide to our Clients, such as when a Client deploys our technology in order to collect, process or transfer first party data ... You can opt out of having your mobile advertising identifiers used for certain types of interest-based (also called “cross-app”) mobile behavioral advertising, by accessing the “settings” on your Apple or Android mobile device, as follows: | U50: https://onesignal.com/privacy_policy
A51: 725 | B51: https://optinmonster.com/ | C51: 45230 | D51: Oliver | E51: 45660 | F51: 0 | H51: 1 | I51: "This information allows ad networks to, among other things, deliver targeted advertisements that they believe will be of most interest to you." | J51: 0 | L51: 1 | M51: Ads appearing on any of our websites may be delivered to users by advertising partners, who may set cookies. These cookies allow the ad server to recognize your computer each time they send you an online advertisement to compile information about you or others who use your computer. This information allows ad networks to, among other things, deliver targeted advertisements that they believe will be of most interest to you. | N51: 0 | P51: 1 | R51: 0 | U51: https://optinmonster.com/privacy/
A52: 731 | B52: http://www.owneriq.com/ | C52: 45216 | D52: Sophie | E52: 45660 | F52: 0 | H52: 1 | I52: With our service, you should receive advertisements that are more relevant to you, based on current browsing and buying behavior, than the standard advertising you would receive otherwise. | J52: 1 | K52: At ownerIQ, we collect data about the products and services that people own, use or have shown interest in, and use that data to help advertisers and publishers (websites and mobile apps that provide products, services, content and media) provide relevant advertising and content to those people | L52: 1 | M52: At ownerIQ, we collect data about the products and services that people own, use or have shown interest in, and use that data to help advertisers and publishers (websites and mobile apps that provide products, services, content and media) provide relevant advertising and content to those people as they browse the internet or utilize an app on a mobile device. For example, if you visit and browse on Website/mobile application A, on a subsequent online visit to Website/mobile application B, you may see ads personalized by your browsing history on Website/mobile application A. This is called Interest Based Advertising. | N52: 1 | O52: If you do not want to receive ads displayed by us based on your browsing and purchasing behavior, you can opt out as described below | P52: 1 | R52: 1 | S52: optout.owneriq.net | U52: https://www.owneriq.com/privacy-notice
A53: 788 | B53: http://www.quantcast.com/ | C53: 45186 | D53: Oliver | E53: 45660 | F53: 0 | H53: 1 | I53: "To provide the Solutions, Quantcast collects and uses Personal Information for various purposes, such as measuring and understanding audiences, targeting and delivering ads, measuring ad performance, and similar related purposes" | J53: 1 | K53: "Identifiers, including IP addresses and other similar Pseudonymous Identifiers. Through automated means Third-party sources" | L53: 1 | M53: As detailed in the chart above, we “sell” or “share” (as such terms are defined in the CCPA) certain categories of Personal Information to and with third parties and have “sold” or “shared” certain categories of Personal Information in the last twelve (12) months. | N53: 1 | O53: "We offer cookie-based and cookieless opt-out methods that allow you to exercise the above-listed rights" | P53: 1 | Q53: Proof by existence of optout | R53: 1 | S53: Cookie named "qoo: OPT_OUT" | T53: Also another method, unclear what it is | U53: https://www.quantcast.com/privacy/ https://www.quantcast.com/privacy-choices/
A54: 846 | B54: http://scribol.com/ | C54: 45216 | D54: Oliver | E54: 45660 | F54: 0 | H54: 1 | I54: "We use third-party advertising companies to serve ads and collect information when users visit our site" | J54: 1 | K54: "We will use the persistent cookies to enable the Site to recognize you when you visit." | L54: 1 | M54: We use third-party advertising companies to serve ads and collect information when users visit our site. These companies may use information (not including your name, address, email address or telephone number) about your visits to this and other websites in order to provide advertisements on our site, other websites and other forms of media about goods and services of interest to you. | N54: 0 | P54: 1 | R54: 0 | U54: https://scribol.com/p/privacy-policy/
A55: 855 | B55: http://sharethrough.com/ | C55: 45184 | D55: Oliver | E55: 45660 | F55: 0 | H55: 1 | I55: "Sharethrough may Process your Personal Data when you visit third-party websites, mobile applications and over-the-top (“OTT”) devices (such as SmartTVs or applications on your Smart TV) (“Partner Sites”), that use our advertising platform (the “Advertising Platform”) to serve targeted advertisements to you based on your personal interests (“Advertisements”)." | J55: 0 | K55: "Sharethrough does not use your Personal Data with any automated decision-making process, including profiling, which may produce a legal effect concerning you or similarly significantly affect you." | L55: 1 | M55: We may share, or have shared, your Personal Information for behavioural advertising purposes over the prior twelve (12) months. This may be referred to as the “sale” of your Personal Information for monetary or other valuable consideration. Sharethrough does not actually “sell” your Personal Information as is commonly understood to require an exchange for money; we simply share it with our clients to provide our services. | N55: 1 | P55: 1 | Q55: Proof by existence of opt out mechanism | R55: 1 | S55: Possibly stx_opt_out=1, opt out available through the DAA | T55: https://privacy-center.sharethrough.com/en/do-not-sell-my-personal-information/ | U55: https://privacy-center.sharethrough.com/en/do-not-sell-my-personal-information/ https://privacy-center.sharethrough.com/en/consumer-privacy-notice/#8
A56: 869 | B56: https://smartyads.com/ | C56: 45186 | D56: Oliver | E56: 45660 | F56: 1 | G56: FingerprintGen | H56: 1 | I56: "Finally, our clients may use third-party data in combination with your user information to deliver targeted advertisement materials and/or inventory across multiple devices that may ultimately be processed by our technology without our knowledge thereof." | J56: 1 | K56: "Therefore, we collect a variety of data using cookies and various other standards (typical for the industry) and unique (if our technology allows so) web technologies to collect information automatically from your device" | L56: 1 | M56: We act on assumption that consumers prefer relevant ads, tailored in accordance with their interests. Therefore, we collect a variety of data using cookies and various other standards (typical for the industry) and unique (if our technology allows so) web technologies to collect information automatically from your device, including: Cookies. ... Tags and Pixels. Tags and Pixels are blocks of code that we and our clients may use to track your browsing on the Internet: from resources to any particular websites or applications to track your browsing behavior. | N56: 1 | O56: Seen on do not sell link page | P56: 1 | Q56: Proof by existence of optout | R56: 0 | U56: https://smartyads.com/privacy-policy https://smartyads.com/ccpa-resource#ccpa-formwrap
A57: 882 | B57: https://www.prposting.com | C57: 45186 | D57: Oliver | E57: 45660 | F57: 0 | H57: 1 | I57: "We target (and measure the performance of) ads to Members, Visitors and others both on and off our Services directly or through a variety of partners" | J57: 1 | K57: "PRPosting Corporation will be the controller of your personal data provided to, or collected by or for, or processed in connection with, our Services." | L57: 1 | M57: We collect data through cookies and similar technologies. As further described in our Cookie Policy , we use cookies and similar technologies (e.g., web beacons, pixels, ad tags and device identifiers) to recognize you and/or your device(s) on, off and across different Services and devices. We also allow some others to use cookies as described in our Cookie Policy. ... We serve you tailored ads both on and off our Services. | N57: 0 | O57: Says there is one, doesn't offer a method | P57: 1 | Q57: Proof by existence of opt out mechanism | R57: 0 | U57: https://prposting.com/privacy-policy.html
A58: 890 | B58: http://www.specificmedia.com/ | D58: Sophie | E58: 45660 | F58: 0 | H58: 1 | I58: we may engage and work with vendors to serve advertisements about us on other online services. Some of these ads may be tailored to your interest based on your browsing of our Online Service and elsewhere on the Internet, which may include use of precise location and/or Cross-device Data, sometimes referred to as “interest-based advertising” | J58: 1 | K58: We may also automatically collect certain information about you when you access or use the Online Service (“Usage Information”). We treat Usage Information as Personal Data to the extent required by applicable law and where it is combined with Personal Data by or on behalf of us. | L58: 1 | M58: As more fully described in Section 2.C, Third-Party Services (defined below) may associate Tracking Technologies with our Online Services and in doing so may collect Personal Data about your online activities over time and across different Web sites when you use our Online Services or Third-Party Services. Without limiting the generality of the forgoing, we may engage and work with vendors to serve advertisements about us on other online services. Some of these ads may be tailored to your interest based on your browsing of our Online Service and elsewhere on the Internet, which may include use of precise location and/or Cross-device Data, sometimes referred to as “interest-based advertising” and “online behavioral advertising” (“Interest-based Advertising”), which may include sending you an ad on another online service after you have left our Online Service (i.e., “retargeting”). | N58: 1 | P58: 1 | R58: 1 | S58: opt out links | U58: https://www.viantinc.com/privacy-center/
A59: 910 | B59: http://www.strikead.com/ | C59: 45230 | D59: Oliver | E59: 45660 | F59: 0 | H59: 0 | J59: 0 | L59: 1 | M59: Embedded content from other websites Articles on this site may include embedded content (e.g. videos, images, articles, etc.). Embedded content from other websites behaves in the exact same way as if the visitor has visited the other website. These websites may collect data about you, use cookies, embed additional third-party tracking, and monitor your interaction with that embedded content, including tracking your interaction with the embedded content if you have an account and are logged in to that website. | N59: 0 | P59: 0 | R59: 0 | U59: https://www.strikead.com/privacy-policy/
A60: 917 | B60: https://www.sunmedia.tv/en/ | C60: 45228 | D60: Oliver | E60: 45660 | F60: 0 | H60: 1 | I60: "The purpose of processing the data we collect is to offer the best advertising campaigns to each user" | J60: 1 | K60: "Whenever the final user visits any of our partner´s sites or any on line add, we assign such user a user unique identifier (a random and unique combination of characters)" | L60: 1 | M60: The purpose of processing the data we collect is to offer the best advertising campaigns to each user, campaigns that are of their interest, in order to be able to be accurate, SUNMEDIA needs to collect certain information. However, SUNMEDIA will not proceed to sale data to any third party without the express authorization of the owners of the data. | N60: 0 | P60: 1 | R60: 0 | U60: https://www.sunmedia.tv/en/cookies-users/
A61: 936 | B61: http://teads.tv/ | C61: 45223 | D61: Sophie | E61: 45660 | F61: 0 | H61: 1 | I61: Teads uses data it collects, including sensitive personal information, to show ads that are based on your browsing activity across non-affiliated websites and apps, combines data collected across its clients to help enhance its products and services, and discloses data to its business partners. | J61: 1 | K61: Teads uses data it collects, including sensitive personal information, to show ads that are based on your browsing activity across non-affiliated websites and apps, combines data collected across its clients to help enhance its products and services, and discloses data to its business partners. | L61: 1 | M61: Teads uses data it collects, including sensitive personal information, to show ads that are based on your browsing activity across non-affiliated websites and apps, combines data collected across its clients to help enhance its products and services, and discloses data to its business partners. Such uses and disclosures may be considered a “sale” or “share” under the CCPA or “targeted advertising” under the other state privacy laws. In the previous 12 months, we may have “sold” or “shared” your personal information to the recipients listed in the table above. | N61: 1 | O61: Button on site | P61: 1 | R61: 1 | S61: viewer-data-deletion cookie | U61: https://privacy-policy.teads.com/privacy-policy/us-privacy-notice/
A62: 968 | B62: http://trafmag.com/ | C62: 45188 | D62: Sophie | E62: 45660 | F62: 0 | H62: 1 | I62: All this information helps us choose the advertisement from our partners, which will be most suitable for you. We choose the advertisements based on your prior activity on the web-pages of on-line stores and the non-personal data we have gathered | J62: 1 | K62: Our technique presupposes the usage of non-personal data only. This data contains the history of the web-sites you have visited, advertising links you have followed, the goods you have viewed on the pages of on-line stores, the goods you have added to cart and so on | L62: 1 | M62: All this information helps us choose the advertisement from our partners, which will be most suitable for you. We choose the advertisements based on your prior activity on the web-pages of on-line stores and the non-personal data we have gathered. This helps us to eliminate from the sites those advertising offers that are of little interest to you. Thus, the income of partner-sites is raised, as they can develop more dynamically and provide you with better service. | N62: 1 | O62: If you do not wish to receive advertising chosen according to our technique, you can disable the option through the link. In this case, the TrafMag cookie will be installed to your browser. It will prompt our system not to gather your non-personal data. | P62: 1 | Q62: Proof by existence of optout | R62: 1 | S62: ga.js | U62: https://trafmag.com/index.php?page=policy
A63: 981 | B63: https://twilio.com | C63: 45216 | D63: Sophie | E63: 45660 | F63: 1 | G63: EmailAgg | H63: 1 | I63: "share personal data for cross-context behavioral advertising" | J63: 1 | K63: "Twilio collects personal data such as Customer Account Data directly from you — as a customer or a visitor — when you visit Twilio’s website" | L63: 1 | M63: First things first: we do not sell your personal data, ... We also do not allow any personal data to be used by third parties for their own marketing purposes (except in cases where you explicitly request or provide consent for us to do so, such as at a conference when you direct us to share your information with a sponsor). However, we do need to share it in some circumstances. These may be to provide you services ... or share personal data for cross-context behavioral advertising. ... Twilio uses common information-gathering tools such as cookies, web beacons, pixels and other similar tracking technologies to automatically collect information as you navigate our websites, our services or when you interact with emails we sent to you. ... Global Privacy Control. Global Privacy Control (GPC) is a technical specification that you can use to inform websites of your privacy preferences in regard to ad trackers. To set up GPC, you can visit the Global Privacy Control page. If you do choose to set up GPC, we will automatically turn off all non-required cookies on Twilio’s websites for you. Please note that this may impact the functionality of our websites or your account. Opting out of Advertising Cookies. To learn more about how to opt out of targeting and advertising cookies, you can go to the Your Online Choices page, ... | N63: 1 | O63: You can opt out of receiving marketing communications from us at any time through your marketing preferences page by clicking the “unsubscribe” link at the bottom of any marketing email you receive from Twilio. | P63: 1 | R63: 1 | U63: https://www.twilio.com/en-us/legal/privacy
A64: 985 | B64: https://www.ucfunnel.com/ | C64: 45227 | D64: Sophie | E64: 45660 | H64: 1 | I64: Particular advertising-related purposes for which ucfunnel clients may use the non-PII they collect on the platform for interest-based advertising in various formats, regions, sequence, and report users respond to ads and aggregated statistics regarding, for example, the effectiveness of online advertising campaigns. | J64: 1 | K64: By saving information in a cookie, websites and servers can remember preferences or recognize browsers from one visit to another or from one website to another. To make our services when users use the service, identify a user's information or data, the system will record the user behavior, such as the cookie. | L64: 1 | M64: Through the Platform, we may (but do not necessarily, or always) collect a variety of information about end users. The Platform uses mainly cookies, pixels, beacons, tags, device-based SDKs, and in some cases non-cookie technologies, to collect non-PII associated with particular web browsers or devices. ... The Platform enables ucfunnel's clients to use non-PII they collect to buy and sell online advertising, including interest-based advertising, using real-time bidding. | N64: 0 | P64: 1 | R64: 0 | U64: https://www.ucfunnel.com/privacy-policy
A65: 997 | B65: http://www.various.com/ | C65: 45216 | D65: Sophie | E65: 45660 | F65: 0 | H65: 1 | I65: We, or a data provider or advertiser that we have engaged, may also place or recognize a cookie on your browser to enable you to receive customized ads or content. | J65: 1 | K65: "We collect Personal Information when you use or interact with our Services, including when you register with us, create a profile, browse our products online, and make purchases from us (including processing of payment)." | L65: N/A | M65: No privacy policy | N65: N/A | O65: No privacy policy | P65: N/A | Q65: No privacy policy | R65: N/A | S65: No privacy policy | T65: No privacy policy | U65: N/A
A66: 1013 | B66: https://vicinity.media/ | C66: 45228 | D66: Sophie | E66: 45660 | F66: 1 | G66: FingerprintInv | H66: 1 | I66: At a subsequent visit to the same website, you will be identified as a previous visitor and the website is aware of your previous visit/ s and/ or transaction/ s and/ or conduct. This illustrates what is called your browsing activity or history and preferences, which enables better, targeted advertising to you, amongst other things. | J66: 1 | K66: Vicinity collects user personal information electronically, when you use/ access the website and/ or partner websites. | L66: 1 | M66: Vicinity makes use of ‘cookies’, which is information in the form of a small file that is sent by your web browser from a website that you click on/ visit to your electronic device’s hard drive, about that website. At a subsequent visit to the same website, you will be identified as a previous visitor and the website is aware of your previous visit/ s and/ or transaction/ s and/ or conduct. This illustrates what is called your browsing activity or history and preferences, which enables better, targeted advertising to you, amongst other things. | N66: 0 | P66: 1 | R66: 0 | U66: https://vicinity.media/privacy-policy/
A67: 1016 | B67: http://www.healthcentralcorp.com/ | C67: 45233 | D67: Oliver | E67: 45660 | F67: 1 | G67: FingerprintingInv | H67: 1 | I67: "By way of example, as you browse our Site, cookies may be placed on your computer so that we can understand what you are interested in. Our advertising partners then enable us to present you with retargeted advertising on other sites based on your previous interaction with our Site" | J67: 1 | K67: "The following information, some of which may constitute Personal Information, is collected automatically when you access or use the Site: Cookies do not typically contain information that individually identifies you, but Personal Information that we store about you may be linked to the information stored in and obtained from cookie" | L67: 1 | M67: You have a right to opt out of the sale of Personal Information. You may, at any time, direct us to not sell Personal Information about you to third parties. | N67: 1 | P67: 1 | R67: 0 | U67: https://www.healthcentralcorp.com/privacy-policy
A68: 1018 | B68: https://verve.com/ | C68: 45216 | D68: Oliver | E68: 45660 | F68: 0 | H68: 1 | I68: "Mobile advertising identifiers, session and persistent cookies, IP addresses, apps used or downloaded, web sites visited, browser and operating system type, type of device used, information actively provided by users responding to a form in an ad, randomly assigned identifiers, precise and general location information and system information that our SDK may collect about your device or network provider." | J68: 1 | K68: "Mobile advertising identifiers, session and persistent cookies, IP addresses, apps used or downloaded, web sites visited, browser and operating system type, type of device used, information actively provided by users responding to a form in an ad, randomly assigned identifiers, precise and general location information and system information that our SDK may collect about your device or network provider." | L68: 1 | M68: If a Verve publisher or advertiser partner has transmitted to Verve a “Do Not Sell or Share My Personal Information” signal, an “Opt-Out of the Use of My Personal Information for Interest-Based Advertising” signal, or a “Limit Use of My Sensitive Personal Information” signal, we will limit our use of Personal Information from that partner and we will act only as a service provider as defined in the CCPA. You may also exercise your opt-out rights as described below. | N68: 1 | O68: "Please email us at ccpa@verve.com for instructions for how you can exercise your California access, deletion and Opt-Out rights." | P68: 1 | R68: 0 | U68: https://verve.com/product-privacy-policies/#California-Residents
A69: 1061 | B69: https://www.yieldify.com/ | C69: 45227 | D69: Sophie | E69: 45660 | F69: 0 | H69: 1 | I69: To deliver relevant website content and advertisements to you and measure or understand the effectiveness of the advertising we serve to you | J69: 1 | K69: Automated technologies or interactions. As you interact with our website, we may automatically collect Technical Data about your equipment, browsing actions and patterns. We collect this personal data by using cookies, and other similar technologies. | L69: 1 | M69: We may have to share your personal data with the parties set out below for the purposes set out in the table in paragraph 4 above: ... Professional services and technology providers such as marketing agencies, advertising partners, website and landing page hosts and marketing and sales technology companies, such as CRM or Marketing Automation tools, who help us run our business. | N69: 0 | P69: 1 | R69: 0 | U69: https://www.yieldify.com/privacy-accessibility/
A70: 1075 | B70: https://www.carbonads.net/ | C70: 45233 | D70: Oliver | E70: 45660 | F70: 0 | H70: 1 | I70: "As part of the buying and selling process and related transactions in our marketplace Services, we facilitate the sharing of information, which may include some Personally Identifiable Information, between our publisher and advertiser users who work directly with each other." | J70: 1 | K70: "We may link some of this automatically-collected data to certain Personally Identifiable Information." | L70: 1 | M70: "As part of the buying and selling process and related transactions in our marketplace Services, we facilitate the sharing of information, which may include some Personally Identifiable Information, between our publisher and advertiser users who work directly with each other." | N70: 0 | P70: 1 | R70: 0 | U70: https://www.buysellads.com/privacy?
A71: 1081 | B71: https://www.yotpo.com/ | C71: 45215 | D71: Oliver | E71: 45660 | F71: 1 | G71: Email, EmailAgg | H71: 1 | I71: "This includes contextual, behavioral and interests-based advertising based on Client’s activity, preferences or other data available to us or to our business partners." | J71: 1 | K71: "We collect such data either automatically, through the data subject’s interaction with us or with our Sites or Services; or through third-party services, social media, analytics tools, events we organize or participate in, and other business initiatives" | L71: 1 | M71: We do not sell or “share” your personal information for the intents and purposes of the CCPA or CPRA, nor disclose personal information that we “control” to any third party for their direct marketing purposes. We may disclose personal data to third parties or allow them to collect personal data from our Services as described in Section ‎5 above, if those third parties are our customers (in respect of Client-Owned Data processed on their behalf), or our authorized Service Providers or business partners who have agreed to our contractual limitations as to their retention, use, and disclosure of such personal data, or if you integrate the services of third parties with our Services, or direct us to disclose your personal data to third parties, or as otherwise described in Section 5 above. | N71: 0 | P71: 1 | R71: 0 | U71: https://www.yotpo.com/privacy-policy/
B72: Total Sites | F72: Crosslisted | H72: Targeted Advertising | J72: Profiling | L72: Selling | N72: Setting: To Opt Out | P72: Selling By Default | R72: Sign of not selling
A73: Totals | B73: =COUNTIF(B1:B71,"<>") - 1 -> 70 | F73: =COUNTIF(F2:F71,"1") -> 15 | H73: =COUNTIF(H2:H71,"1") -> 65 | J73: =COUNTIF(J2:J71,"1") -> 61 | L73: =COUNTIF(L2:L71,"1") -> 63 | N73: =COUNTIF(N2:N71,"1") -> 39 | P73: =COUNTIF(P2:P71,"1") -> 63 | R73: =COUNTIF(R2:R71,"1") -> 15

Sheet Analytics
A1: ID | B1: Network URL [URL] | C1: Date of Analysis [DATE] | D1: Reviewer [Name] | E1: Date of Selling/Sharing (Buying/Collecting) Doublechecked by SZ [DATE] | F1: Crosslisted [0, 1] | G1: Crosslisted Category [Category Name] | H1: Targeted Advertising [0, 1] | I1: Evidence | J1: Profiling [0, 1] | K1: Evidence | L1: Selling/ Sharing (Buying/Collecting) [0, 1] | M1: Evidence | N1: Setting: To Opt Out [0, 1] | O1: Evidence | P1: Selling By Default [0, 1] | Q1: Evidence | R1: Sign of Not Selling [0, 1] | S1: What is it [Name of Tag] | T1: Evidence | U1: Relevant URL [URL] | V1: Crosslisted with Advertising + Selling [0,1] | W1: Crosslisted with Advertising + Targeted Advertising [0,1] | X1: Crosslisted with Advertising + Profiling [0,1] | Y1: Crosslisted with FingerprintGen + Selling [0,1] | Z1: Crosslisted with FingerprintGen + Targeted Advertising [0,1] | AA1: Crosslisted with FingerprintGen + Profiling [0,1]
A2: 18 | B2: http://automattic.com/ | C2: 45187 | D2: Oliver | E2: N/A | F2: 1 | G2: Advertising Content | H2: 1 | I2: "Automattic uses cookies and other technologies like pixel tags to help us identify and track visitors, usage, and access preferences for our Services, as well as track and understand email campaign effectiveness and to deliver targeted ads." | J2: 1 | K2: "We also collect some information automatically: Information from cookies & other technologies Interactions with other users’ sites Location information" | L2: 1 | M2: "To the extent that we share your information with certain advertising, marketing, or analytics vendors, this can be considered a “sale” or “share” in certain U.S. States, which you may have the right to opt out of." | N2: 1 | O2: "You can learn more about this sharing and how to opt out by clicking the “Do Not Sell My Personal Information” link in the footer of our websites, or from the settings page within our apps." | P2: 1 | Q2: Proof by existence of optout | R2: 1 | S2: In a cookie | T2: "Our opt-out is managed through cookies, so if you delete cookies, your browser is set to delete cookies automatically after a certain length of time, or if you visit sites in a different browser, you’ll need to make this selection again." | U2: https://automattic.com/privacy/ | V2: =IF(ISNUMBER(SEARCH("Advertising", G2)), IF(L2 = 1, 1, 0), "") -> 1 | W2: =IF(ISNUMBER(SEARCH("Advertising", G2)), IF(H2 = 1, 1, 0), "") -> 1 | X2: =IF(ISNUMBER(SEARCH("Advertising", G2)), IF(J2 = 1, 1, 0), "") -> 1 | Y2: =IF(ISNUMBER(SEARCH("FingerprintGen", G2)), IF(L2 = 1, 1, 0), "") | Z2: =IF(ISNUMBER(SEARCH("FingerprintGen", G2)), IF(H2 = 1, 1, 0), "") | AA2: =IF(ISNUMBER(SEARCH("FingerprintGen", G2)), IF(J2 = 1, 1, 0), "")
A3: 24 | B3: http://www.blogcounter.de/ | C3: 45188 | D3: Sophie | E3: N/A | F3: 0 | H3: 1 | I3: Advertising Cookies. Advertising Cookies are used to serve you with advertisements that may be relevant to you and your interests. | J3: 1 | K3: We may also collect information how the Service is accessed and used (“Usage Data”). This Usage Data may include information such as your computer’s Internet Protocol address (e.g. IP address), browser type, browser version, the pages of our Service that you visit, the time and date of your visit, the time spent on those pages, unique device identifiers and other diagnostic data. | L3: 0 | M3: We use your data to provide and improve the Service. By using the Service, you agree to the collection and use of information in accordance with this policy. | N3: 0 | U3: https://www.opensourcecms.com/privacy-policy/ | V3: =IF(ISNUMBER(SEARCH("Advertising", G3)), IF(L3 = 1, 1, 0), "") | W3: =IF(ISNUMBER(SEARCH("Advertising", G3)), IF(H3 = 1, 1, 0), "") | X3: =IF(ISNUMBER(SEARCH("Advertising", G3)), IF(J3 = 1, 1, 0), "") | Y3: =IF(ISNUMBER(SEARCH("FingerprintGen", G3)), IF(L3 = 1, 1, 0), "") | Z3: =IF(ISNUMBER(SEARCH("FingerprintGen", G3)), IF(H3 = 1, 1, 0), "") | AA3: =IF(ISNUMBER(SEARCH("FingerprintGen", G3)), IF(J3 = 1, 1, 0), "")
A4: 49 | B4: http://www.convert.com/ | C4: 45188 | D4: Sophie | E4: N/A | F4: 0 | H4: 1 | I4: Personalize and customize our content and to give you the best user experience and to enable you to participate in interactive features of our Website. | J4: 1 | K4: Automatic information (some of which can be personal data) about your visits to our Website which will include (but are not limited to) your IP address, online tracking such as location, browser and type of device you use and your operating system, | L4: 1 | M4: Allow authorized third parties (for a list of our authorized third parties see here) to track and store information about visitors to our website (including IP addresses). Disclose your personal data to those who are providing services to us if they have appropriate processes to protect it. | N4: 1 | O4: Our customers can place an opt-out link on their website and we respect your privacy when you turn off tracking features and other security settings in your browser. | P4: 1 | Q4: Proof by existence of optout | R4: 1 | S4: opt-out link on their website that can be used by visitors to their websites who do not want their information given to us | U4: https://www.convert.com/privacy-notice/ | V4: =IF(ISNUMBER(SEARCH("Advertising", G4)), IF(L4 = 1, 1, 0), "") | W4: =IF(ISNUMBER(SEARCH("Advertising", G4)), IF(H4 = 1, 1, 0), "") | X4: =IF(ISNUMBER(SEARCH("Advertising", G4)), IF(J4 = 1, 1, 0), "") | Y4: =IF(ISNUMBER(SEARCH("FingerprintGen", G4)), IF(L4 = 1, 1, 0), "") | Z4: =IF(ISNUMBER(SEARCH("FingerprintGen", G4)), IF(H4 = 1, 1, 0), "") | AA4: =IF(ISNUMBER(SEARCH("FingerprintGen", G4)), IF(J4 = 1, 1, 0), "")
A5: 53 | B5: https://www.crownpeak.com/ | C5: 45188 | D5: Sophie | E5: N/A | F5: 0 | H5: 1 | I5: To personalise the marketing messages we send by analysing the details of the products and services you have with us. | J5: 1 | K5: Your name, job title, contact details (e.g., phone number, email address, postal address or mobile number) and authentication details (e.g., user identification number, username, password to access the services). | L5: 1 | M5: Service providers and business partners that perform services on our behalf, including improving functionality of our platforms and websites, collecting information about you and assisting us with IT and social media management and data analytics. ... If you would like to exercise these rights please submit a request, with a description of the nature of your request and the Personal Data at issue. ... Right: In relation to automated decision-making and profiling | N5: 0 | U5: https://www.crownpeak.com/policies/privacy-policy/ | V5: =IF(ISNUMBER(SEARCH("Advertising", G5)), IF(L5 = 1, 1, 0), "") | W5: =IF(ISNUMBER(SEARCH("Advertising", G5)), IF(H5 = 1, 1, 0), "") | X5: =IF(ISNUMBER(SEARCH("Advertising", G5)), IF(J5 = 1, 1, 0), "") | Y5: =IF(ISNUMBER(SEARCH("FingerprintGen", G5)), IF(L5 = 1, 1, 0), "") | Z5: =IF(ISNUMBER(SEARCH("FingerprintGen", G5)), IF(H5 = 1, 1, 0), "") | AA5: =IF(ISNUMBER(SEARCH("FingerprintGen", G5)), IF(J5 = 1, 1, 0), "")
A6: 64 | B6: https://www.eff.org/ | C6: 45187 | D6: Oliver | E6: N/A | F6: 0 | H6: 0 | J6: 0 | L6: 0 | M6: "EFF does not sell or rent member, donor or website visitor information under any circumstances, and we do not share member, donor or visitor information without prior consent except as compelled by law." | N6: 0 | P6: 0 | R6: 0 | U6: https://www.eff.org/policy It's a site about preserving internet privacy | V6: =IF(ISNUMBER(SEARCH("Advertising", G6)), IF(L6 = 1, 1, 0), "") | W6: =IF(ISNUMBER(SEARCH("Advertising", G6)), IF(H6 = 1, 1, 0), "") | X6: =IF(ISNUMBER(SEARCH("Advertising", G6)), IF(J6 = 1, 1, 0), "") | Y6: =IF(ISNUMBER(SEARCH("FingerprintGen", G6)), IF(L6 = 1, 1, 0), "") | Z6: =IF(ISNUMBER(SEARCH("FingerprintGen", G6)), IF(H6 = 1, 1, 0), "") | AA6: =IF(ISNUMBER(SEARCH("FingerprintGen", G6)), IF(J6 = 1, 1, 0), "")
A7: 68 | B7: http://extremetracking.com/ | C7: 45188 | D7: Sophie | E7: N/A | F7: 0 | H7: 0 | J7: 1 | K7: While it's not up to us which data we receive, it typically includes items such as IP addresses and website performance data derived from browser activity. | L7: 0 | M7: None of your personal information will be disclosed to anyone without your explicit permission. | N7: 0 | U7: https://extremetracking.com/?policy | V7: =IF(ISNUMBER(SEARCH("Advertising", G7)), IF(L7 = 1, 1, 0), "") | W7: =IF(ISNUMBER(SEARCH("Advertising", G7)), IF(H7 = 1, 1, 0), "") | X7: =IF(ISNUMBER(SEARCH("Advertising", G7)), IF(J7 = 1, 1, 0), "") | Y7: =IF(ISNUMBER(SEARCH("FingerprintGen", G7)), IF(L7 = 1, 1, 0), "") | Z7: =IF(ISNUMBER(SEARCH("FingerprintGen", G7)), IF(H7 = 1, 1, 0), "") | AA7: =IF(ISNUMBER(SEARCH("FingerprintGen", G7)), IF(J7 = 1, 1, 0), "")
A8: 98 | B8: http://www.hubspot.com/ | C8: 45187 | D8: Oliver | E8: N/A | F8: 1 | G8: Email Aggressive | H8: 1 | I8: "Our ad network partner uses cookies and web beacons to collect information about your activities on this and other websites to provide you targeted advertising based upon your interests" | J8: 1 | K8: "For these purposes we do link this automatically-collected data to other personal data provided by you such as name, email address, address, and phone number." | L8: 0 | M8: "Not a Sale. The parties acknowledge and agree that the disclosure of California Personal Information by the Customer to HubSpot does not form part of any monetary or other valuable consideration exchanged between the parties." | N8: 0 | P8: 0 | R8: 0 | U8: https://legal.hubspot.com/legal-stuff https://legal.hubspot.com/dpa | V8: =IF(ISNUMBER(SEARCH("Advertising", G8)), IF(L8 = 1, 1, 0), "") | W8: =IF(ISNUMBER(SEARCH("Advertising", G8)), IF(H8 = 1, 1, 0), "") | X8: =IF(ISNUMBER(SEARCH("Advertising", G8)), IF(J8 = 1, 1, 0), "") | Y8: =IF(ISNUMBER(SEARCH("FingerprintGen", G8)), IF(L8 = 1, 1, 0), "") | Z8: =IF(ISNUMBER(SEARCH("FingerprintGen", G8)), IF(H8 = 1, 1, 0), "") | AA8: =IF(ISNUMBER(SEARCH("FingerprintGen", G8)), IF(J8 = 1, 1, 0), "")
A9: 115 | B9: https://neilpatel.com/ | C9: 45187 | D9: Oliver | E9: N/A | F9: 1 | G9: FingerprintGen | H9: 1 | I9: "Advertising cookies – these cookies are used to deliver advertisements that are relevant to you and to your interests." | J9: 1 | K9: "Neil Patel Digital may automatically receive and log certain types of information when you visit or interact with our websites, services, mobile applications or other products" | L9: 1 | M9: "To administer and analyze our client base (purchasing behavior and history) in order to improve the quality, variety, and availability of products/ services offered/provided;" | N9: 1 | O9: "Opt-out of the sale of your Personal Information to certain affiliates and other Third Parties for their marketing purposes. To exercise this right, please submit your request by filling out the form after clicking on this link, or by emailing neil@neilpatel.com. You do not need to verify your identity to opt out. – Or you can go to this page, Do Not Sell My Info." | P9: 1 | Q9: Proof by existence of opt out | R9: 0 | S9: Unclear | U9: https://neilpatel.com/privacy/#gdpr-processing https://neilpatel.com/do-not-track/ | V9: =IF(ISNUMBER(SEARCH("Advertising", G9)), IF(L9 = 1, 1, 0), "") | W9: =IF(ISNUMBER(SEARCH("Advertising", G9)), IF(H9 = 1, 1, 0), "") | X9: =IF(ISNUMBER(SEARCH("Advertising", G9)), IF(J9 = 1, 1, 0), "") | Y9: =IF(ISNUMBER(SEARCH("FingerprintGen", G9)), IF(L9 = 1, 1, 0), "") -> 1 | Z9: =IF(ISNUMBER(SEARCH("FingerprintGen", G9)), IF(H9 = 1, 1, 0), "") -> 1 | AA9: =IF(ISNUMBER(SEARCH("FingerprintGen", G9)), IF(J9 = 1, 1, 0), "") -> 1
A10: 121 | B10: http://www.liveperson.net/ | C10: 45188 | D10: Sophie | E10: N/A | F10: 0 | H10: 1 | I10: LivePerson uses information you provide through various channels for ordinary business activities, including: To deliver marketing materials to you, | J10: 1 | K10: Information you provide to us, such as: Personal information, such as your name and contact information; | L10: 0 | M10: LivePerson does not sell or trade personal information provided by you to us in any transcript, survey or recording for purposes of direct marketing. | N10: 0 | U10: https://www.liveperson.com/policies/privacy | V10: =IF(ISNUMBER(SEARCH("Advertising", G10)), IF(L10 = 1, 1, 0), "") | W10: =IF(ISNUMBER(SEARCH("Advertising", G10)), IF(H10 = 1, 1, 0), "") | X10: =IF(ISNUMBER(SEARCH("Advertising", G10)), IF(J10 = 1, 1, 0), "") | Y10: =IF(ISNUMBER(SEARCH("FingerprintGen", G10)), IF(L10 = 1, 1, 0), "") | Z10: =IF(ISNUMBER(SEARCH("FingerprintGen", G10)), IF(H10 = 1, 1, 0), "") | AA10: =IF(ISNUMBER(SEARCH("FingerprintGen", G10)), IF(J10 = 1, 1, 0), "")
A11: 156 | B11: http://www.oewa.at/ | C11: 45188 | D11: Sophie | E11: N/A | F11: 0 | H11: 0 | J11: 0 | L11: 0 | M11: We do not transmit any personal data to external controllers. | N11: 0 | U11: https://oewa.at/datenschutz/ | V11: =IF(ISNUMBER(SEARCH("Advertising", G11)), IF(L11 = 1, 1, 0), "") | W11: =IF(ISNUMBER(SEARCH("Advertising", G11)), IF(H11 = 1, 1, 0), "") | X11: =IF(ISNUMBER(SEARCH("Advertising", G11)), IF(J11 = 1, 1, 0), "") | Y11: =IF(ISNUMBER(SEARCH("FingerprintGen", G11)), IF(L11 = 1, 1, 0), "") | Z11: =IF(ISNUMBER(SEARCH("FingerprintGen", G11)), IF(H11 = 1, 1, 0), "") | AA11: =IF(ISNUMBER(SEARCH("FingerprintGen", G11)), IF(J11 = 1, 1, 0), "")
A12: 157 | B12: http://parsely.com/ | C12: 45187 | D12: Oliver | E12: N/A | F12: 0 | H12: 1 | I12: "WPVIP uses cookies and other technologies like pixel tags to help us identify and track visitors, usage, and access preferences for our Services, as well as track and understand email campaign effectiveness and to deliver targeted ads" | J12: 1 | K12: "We also collect some information automatically about your interactions with us or our Services, including: Activity, Device and Usage information Information from cookies & other technologies" | L12: 1 | M12: "We never directly sell your personal information in the conventional sense (i.e., for money), but in some U.S. states the sharing of your information with advertising/analytics vendors can be considered a “sale” of your information, which you may have the right to opt out of" | N12: 1 | O12: "Our opt-out is managed through cookies, so if you delete cookies, your browser is set to delete cookies automatically after a certain length of time, or if you visit sites in a different browser, you’ll need to make this selection again." | P12: 1 | Q12: Proof by existence of optout | R12: 1 | S12: In a cookie | U12: https://wpvip.com/privacy/#h-your-rights | V12: =IF(ISNUMBER(SEARCH("Advertising", G12)), IF(L12 = 1, 1, 0), "") | W12: =IF(ISNUMBER(SEARCH("Advertising", G12)), IF(H12 = 1, 1, 0), "") | X12: =IF(ISNUMBER(SEARCH("Advertising", G12)), IF(J12 = 1, 1, 0), "") | Y12: =IF(ISNUMBER(SEARCH("FingerprintGen", G12)), IF(L12 = 1, 1, 0), "") | Z12: =IF(ISNUMBER(SEARCH("FingerprintGen", G12)), IF(H12 = 1, 1, 0), "") | AA12: =IF(ISNUMBER(SEARCH("FingerprintGen", G12)), IF(J12 = 1, 1, 0), "")
A13: 167 | B13: http://quinstreet.com/ | C13: 45187 | D13: Oliver | E13: N/A | F13: 1 | G13: Advertising | H13: 1 | I13: "We sold and shared the following categories of personal information to Advertising Partners and data aggregators for the commercial purposes described in this Privacy Notice, including for targeted advertising" | J13: 1 | K13: "We collect profile inferences that we draw from your information and web activity to create a personalized profile so we can better identify goods and services that may be of interest. This data may be sold or shared as described in more detail in our Privacy Notice." | L13: 1 | M13: "We may “sell” or “share” personal information as those terms are defined under applicable law, and as indicated for each relevant category of personal information below." | N13: 1 | O13: "To take advantage of your right to opt out of the sale or sharing of personal information or to opt out of targeted advertising, please click here, which is also on our website footer" (https://privacy-central.securiti.ai/#/dsr/1b319101-f00c-470f-a7f0-26aa81f057b8) | P13: 1 | Q13: Proof by existence of optout | R13: 0 | S13: Unclear | U13: https://www.quinstreet.com/privacy-notice/ | V13: =IF(ISNUMBER(SEARCH("Advertising", G13)), IF(L13 = 1, 1, 0), "") -> 1 | W13: =IF(ISNUMBER(SEARCH("Advertising", G13)), IF(H13 = 1, 1, 0), "") -> 1 | X13: =IF(ISNUMBER(SEARCH("Advertising", G13)), IF(J13 = 1, 1, 0), "") -> 1 | Y13: =IF(ISNUMBER(SEARCH("FingerprintGen", G13)), IF(L13 = 1, 1, 0), "") | Z13: =IF(ISNUMBER(SEARCH("FingerprintGen", G13)), IF(H13 = 1, 1, 0), "") | AA13: =IF(ISNUMBER(SEARCH("FingerprintGen", G13)), IF(J13 = 1, 1, 0), "") | AB13: =IF(G12 = "*Advertising*", IF(J12 = 1, 1, 0), "")
A14: 175 | B14: https://www.revtrax.com/ | C14: 45187 | D14: Oliver | E14: N/A | F14: 0 | H14: 0 | J14: 0 | K14: "Usage Data are the information that is sent automatically to RevTrax’s servers when a User is presented with a Web-based offer. This information includes a User’s device type, operating system version, and Internet browser type and version." | L14: 0 | M14: "RevTrax does not sell the Personal Information of consumers who interact with the RevTrax Technology." | N14: 0 | P14: 0 | R14: 0 | U14: https://www.revtrax.com/privacy-policy/ | V14: =IF(ISNUMBER(SEARCH("Advertising", G14)), IF(L14 = 1, 1, 0), "") | W14: =IF(ISNUMBER(SEARCH("Advertising", G14)), IF(H14 = 1, 1, 0), "") | X14: =IF(ISNUMBER(SEARCH("Advertising", G14)), IF(J14 = 1, 1, 0), "") | Y14: =IF(ISNUMBER(SEARCH("FingerprintGen", G14)), IF(L14 = 1, 1, 0), "") | Z14: =IF(ISNUMBER(SEARCH("FingerprintGen", G14)), IF(H14 = 1, 1, 0), "") | AA14: =IF(ISNUMBER(SEARCH("FingerprintGen", G14)), IF(J14 = 1, 1, 0), "")
A15: 208 | B15: https://www.tracify.ai/ | C15: 45187 | D15: Oliver | E15: N/A | F15: 1 | G15: FingerprintInv | H15: 1 | I15: "This processing constitutes: a sale according to the CCPA, VCDPA, CPA, CTDPA and UCPA targeted advertising according to the CPA, CTDPA and UCPA" | J15: 1 | K15: "Personal Data may be freely provided by the User, or, in case of Usage Data, collected automatically when using this Website." | L15: 1 | M15: "Facebook Ads conversion tracking (Facebook pixel) (Meta Platforms Ireland Limited)... This processing constitutes: a sale according to the CCPA, VCDPA, CPA, CTDPA and UCPA targeted advertising according to the CPA, CTDPA and UCPA" | N15: 1 | O15: "To fully exercise your right to opt out you can contact us at any time, using the contact details provided in this document. For a simplified opt-out method you can also use the privacy choices link provided on this Website." | P15: 1 | Q15: Proof by existence of optout | R15: 0 | S15: Can not find aforementioned privacy choices link | U15: https://www.tracify.ai/pages/privacy-policy#california_info | V15: =IF(ISNUMBER(SEARCH("Advertising", G15)), IF(L15 = 1, 1, 0), "") | W15: =IF(ISNUMBER(SEARCH("Advertising", G15)), IF(H15 = 1, 1, 0), "") | X15: =IF(ISNUMBER(SEARCH("Advertising", G15)), IF(J15 = 1, 1, 0), "") | Y15: =IF(ISNUMBER(SEARCH("FingerprintGen", G15)), IF(L15 = 1, 1, 0), "") | Z15: =IF(ISNUMBER(SEARCH("FingerprintGen", G15)), IF(H15 = 1, 1, 0), "") | AA15: =IF(ISNUMBER(SEARCH("FingerprintGen", G15)), IF(J15 = 1, 1, 0), "")
A16: 241 | B16: http://www.zendesk.com/ | C16: 45187 | D16: Oliver | E16: N/A | F16: 0 | H16: 1 | I16: "we share information with advertising partners and allow advertising partners to collect information from our Digital Properties." | J16: 1 | K16: "Information automatically collected, including technical information about your interactions with our Digital Properties (such as IP address, browsing preferences, and purchase history)." | L16: 1 | M16: "Although we have not “sold” or “shared” personal data for money in the past 12 months, we engage in routine practices with our Digital Properties involving third parties that could be considered a “sale” or “sharing” as defined under California law." | N16: 1 | O16: "California residents may request to exercise the Right to Know, the Right to Delete, and the Right to Correct by using our webform or by emailing us at privacy@zendesk.com." | P16: 1 | Q16: Proof by existence of optout | R16: 0 | U16: https://www.zendesk.com/company/agreements-and-terms/privacy-notice/ | V16: =IF(ISNUMBER(SEARCH("Advertising", G16)), IF(L16 = 1, 1, 0), "") | W16: =IF(ISNUMBER(SEARCH("Advertising", G16)), IF(H16 = 1, 1, 0), "") | X16: =IF(ISNUMBER(SEARCH("Advertising", G16)), IF(J16 = 1, 1, 0), "") | Y16: =IF(ISNUMBER(SEARCH("FingerprintGen", G16)), IF(L16 = 1, 1, 0), "") | Z16: =IF(ISNUMBER(SEARCH("FingerprintGen", G16)), IF(H16 = 1, 1, 0), "") | AA16: =IF(ISNUMBER(SEARCH("FingerprintGen", G16)), IF(J16 = 1, 1, 0), "")
B17: Total Sites | F17: Crosslisted | G17: Crosslisted with Advertising | H17: Targeted Advertising | J17: Profiling | L17: Selling | N17: Setting: To Opt Out | P17: Selling By Default | R17: Sign of not selling | V17: Total Crosslisted with Advertising + Selling | W17: Total Crosslisted with Advertising + Targeting | X17: Total Crosslisted with Advertising + Profiling | Y17: Total Crosslisted with FingerprintGen + Selling | Z17: Total Crosslisted with FingerprintGen + Targeting | AA17: Total Crosslisted with FingerprintGen + Profiling
A18: Totals | B18: =COUNTIF(B1:B16,"<>") - 1 -> 15 | F18: =COUNTIF(F2:F16,"1") -> 5 | G18: =COUNTIF(G2:G16,"*Advertising*") -> 2 | H18: =COUNTIF(H2:H16,"1") -> 11 | J18: =COUNTIF(J2:J16,"1") -> 12 | L18: =COUNTIF(L2:L16,"1") -> 8 | N18: =COUNTIF(N2:N16,"1") -> 7 | P18: =COUNTIF(P2:P16,"1") -> 7 | R18: =COUNTIF(R2:R16,"1") -> 3 | V18: =SUM(V2:V16) -> 2 | W18: =SUM(W2:W16) -> 2 | X18: =SUM(X2:X16) -> 2 | Y18: =SUM(Y2:Y16) -> 1 | Z18: =SUM(Z2:Z16) -> 1 | AA18: =SUM(AA2:AA16) -> 1
G19: Crosslisted with FingerprintGen
G20: =COUNTIF(G2:G16,"*FingerprintGen*") -> 1

Sheet FingerprintGen
A1: ID | B1: Network URL [URL] | C1: Date of Analysis [DATE] | D1: Reviewer [Name] | E1: Date of Selling/Sharing (Buying/Collecting) Doublechecked by SZ [DATE] | F1: Crosslisted [0, 1] | G1: Crosslisted Category [Category Name] | H1: Targeted Advertising [0, 1] | I1: Evidence | J1: Profiling [0, 1] | K1: Evidence | L1: Selling/Sharing (Buying/Collecting) [0, 1] | M1: Evidence | N1: Setting: To Opt Out [0, 1] | O1: Evidence | P1: Selling By Default [0, 1] | Q1: Evidence | R1: Sign of Not Selling [0, 1] | S1: What is it [Name of Tag] | T1: Evidence | U1: Relevant URL [URL] | V1: Crosslisted with Advertising + Selling [0,1] | W1: Crosslisted with Advertising + Targeted Advertising [0,1] | X1: Crosslisted with Advertising + Profiling [0,1]
A2: 1 | B2: http://www.adobe.com/ | C2: 45215 | D2: Oliver | E2: 45660 | F2: 1 | G2: Email EmailAgg Content Advertising Analytics | H2: 1 | I2: "We also disclose personal information to other companies in the Adobe family and with advertising and sales partners consistent with your choices" | J2: 1 | K2: "In addition, when you see or interact with these buttons, tools, or content, or view an Adobe web page or app containing them, some information from your browser may automatically be sent to the other company. Please read that company’s privacy policy for more information." | L2: 1 | M2: The types of third parties your information may be disclosed to include: our resellers and other sales and advertising partners, retailers, advertisers, ad agencies, advertising networks and platforms, information service providers, fraud monitoring and prevention providers, and publishers | N2: 1 | P2: 1 | R2: 0 | U2: https://www.adobe.com/privacy/policy.html | V2: =IF(ISNUMBER(SEARCH("Advertising", G2)), IF(L2 = 1, 1, 0), "") -> 1 | W2: =IF(ISNUMBER(SEARCH("Advertising", G2)), IF(H2 = 1, 1, 0), "") -> 1 | X2: =IF(ISNUMBER(SEARCH("Advertising", G2)), IF(J2 = 1, 1, 0), "") -> 1
A3: 6 | B3: http://www.avantlink.com/ | C3: 45194 | D3: Sophie | E3: 45660 | F3: 1 | G3: Advertising, Analytics | H3: 0 | J3: 1 | K3: In order to register as an Affiliate or Merchant, Users are required to provide certain identifiers, including contact information (e.g., your name and email address), unique identifiers (e.g., your password), payment details and demographic information (e.g., your zip code). | L3: 1 | M3: These cookies are used to help us improve your user experience and to track, validate and report on Affiliate, Merchant and user activity through the Service and the links. ... Right to Opt-Out of Sales: You have the right to opt-out of the sale of your personal information; however, we do not “sell” personal information, as that term is defined under Applicable State Laws. | N3: 1 | O3: You have the right to opt-out of the sale of your personal information; however, we do not “sell” personal information, as that term is defined under Applicable State Laws. | P3: 1 | Q3: Proof by existence of opt out | R3: 0 | T3: please submit a request to us by either emailing us at privacy@avantlink.com or filling out the contact form on our website (avantlink.com). | U3: https://www.avantlink.com/privacy-policy/ | V3: =IF(ISNUMBER(SEARCH("Advertising", G3)), IF(L3 = 1, 1, 0), "") -> 1 | W3: =IF(ISNUMBER(SEARCH("Advertising", G3)), IF(H3 = 1, 1, 0), "") -> 0 | X3: =IF(ISNUMBER(SEARCH("Advertising", G3)), IF(J3 = 1, 1, 0), "") -> 1
A4: 10 | B4: http://consumable.com/ | C4: 45194 | D4: Oliver | E4: 45660 | F4: 1 | G4: Advertising | H4: 1 | I4: "We and our third party advertising partners may collect and use your personal information for marketing and advertising purposes" | J4: 1 | K4: "We, our service providers and our third party partners may automatically log information about you, your computer or mobile device, and your activity over time on the Service and other online services" | L4: 1 | M4: We do not sell your personal information. Based on our current understanding of the CCPA, we do not “sell” your personal information as defined in the CCPA. However, like many companies online, Consumable uses services provided by Google, Facebook and other advertising companies that track website visitor activity to help deliver interest-based ads to those visitors. We describe this in more detail in the subsection above entitled “Interest-based advertising.” Use of these services may constitute a “sale” of Personal Information under the CCPA where the user has not opted into the tracking. | N4: 0 | O4: Opt-outs offered are through other systems | P4: 1 | Q4: Proof by existence of opt out | R4: 0 | U4: https://consumable.com/privacy-policy/ | V4: =IF(ISNUMBER(SEARCH("Advertising", G4)), IF(L4 = 1, 1, 0), "") -> 1 | W4: =IF(ISNUMBER(SEARCH("Advertising", G4)), IF(H4 = 1, 1, 0), "") -> 1 | X4: =IF(ISNUMBER(SEARCH("Advertising", G4)), IF(J4 = 1, 1, 0), "") -> 1
A5: 11 | B5: http://www.doubleverify.com/ | C5: 45215 | D5: Oliver | E5: 45660 | F5: 1 | G5: Fingerprinting Analytics | H5: 1 | I5: "Advertising cookies are used to make advertising messages more relevant to you and your interests." | J5: 1 | K5: "Cookies and other tracking technologies may be used to collect information about your use of our Websites and Marketing Activities so that we can promote our Solutions in a way tailored to your interests on our Websites, or on other websites when you click on a DoubleVerify advertisement" | L5: 1 | M5: In certain limited circumstances, DoubleVerify may disclose Personal Information in a way that would constitute “selling” or “sharing” under California and similar U.S. state laws. | N5: 1 | P5: 1 | R5: 0 | U5: https://doubleverify.com/cookie-notice/ https://doubleverify.com/privacy-notice/#link2 | V5: =IF(ISNUMBER(SEARCH("Advertising", G5)), IF(L5 = 1, 1, 0), "") | W5: =IF(ISNUMBER(SEARCH("Advertising", G5)), IF(H5 = 1, 1, 0), "") | X5: =IF(ISNUMBER(SEARCH("Advertising", G5)), IF(J5 = 1, 1, 0), "")
A6: 12 | B6: http://www.experian.com/ | C6: 45194 | D6: Sophie | E6: 45660 | F6: 1 | G6: Advertising | H6: 1 | I6: We may share aggregated information (i.e., information about you and other website visitors collectively, but not specifically identifiable to you) and other non-personal, de-identified, or anonymous information we collect with third parties, including affiliates to develop and deliver targeted advertising on our website and on the websites of third parties. | J6: 1 | K6: we also derive information pertaining to: Individual consumers, such as: Gender Marital status Estimated age range Occupation Education level Household status (head of household, spouse, elderly parent, young adult | L6: 1 | M6: You have the right to exercise control over the processing of certain personal information. This includes the right to opt out from the sale, sharing, processing, and use of personal information for sales, certain profiling or targeted advertising, and from the use of sensitive personal information. Opting out also includes your right to limit generation, use, and disclosure of sensitive personal information. You can choose to opt-out of the sale, and/or opt out of processing of data for targeted advertising, and certain profiling activities and limit the use of your sensitive information. | N6: 1 | O6: You can choose to opt-out of the sale of your personal information and data, opt out of processing your data for targeted advertising, and limit the use of your sensitive information. This is not related to your credit report, and will not affect your credit score. | P6: 1 | Q6: Proof by existence of opt out | R6: 1 | S6: DAA Opt Out - http://www.aboutads.info/choices/ | T6: you may visit the DAA opt-out page and opt-out of this cookie tracking if you do not wish to receive targeted advertising. Please visit http://www.aboutads.info/choices/ for more informatio | U6: https://www.experian.com/privacy/us-consumer-data-privacy-policy | V6: =IF(ISNUMBER(SEARCH("Advertising", G6)), IF(L6 = 1, 1, 0), "") -> 1 | W6: =IF(ISNUMBER(SEARCH("Advertising", G6)), IF(H6 = 1, 1, 0), "") -> 1 | X6: =IF(ISNUMBER(SEARCH("Advertising", G6)), IF(J6 = 1, 1, 0), "") -> 1
A7: 15 | B7: https://fanplayr.com/ | C7: 45194 | D7: Oliver | E7: 45660 | F7: 1 | G7: Advertising | H7: 1 | I7: "Personal Data processed for the following purposes and using the following services: Advertising" | J7: 1 | K7: "Personal Data may be freely provided by the User, or, in case of Usage Data, collected automatically when using Fanplayr.com." | L7: 1 | M7: Personal Data processed for the following purposes and using the following services: Advertising Fanplayr Personal Data: geographic position; Tracker; Usage Data ... We collect personal information of consumers between the age of 13 and 16 and won't sell their data unless those consumers have opted-in. | N7: 0 | O7: Referenced a few times but is missing any actual link | P7: 1 | Q7: Proof by reference of opt out | R7: 1 | S7: usprivacy, _iub_cs-X, IUB_DATA | T7: All three can supposedly hold opt out information | U7: https://www.iubenda.com/privacy-policy/43327124 https://www.fanplayr.com/legal https://www.iubenda.com/privacy-policy/43327124/legal | V7: =IF(ISNUMBER(SEARCH("Advertising", G7)), IF(L7 = 1, 1, 0), "") -> 1 | W7: =IF(ISNUMBER(SEARCH("Advertising", G7)), IF(H7 = 1, 1, 0), "") -> 1 | X7: =IF(ISNUMBER(SEARCH("Advertising", G7)), IF(J7 = 1, 1, 0), "") -> 1
A8: 18 | B8: http://www.google.com/ | C8: 45194 | D8: Oliver | E8: 45660 | F8: 1 | G8: Anti-Fraud Social Email Advertising Content Analytics | H8: 1 | I8: "We use automated systems that analyze your content to provide you with things like customized search results, personalized ads, or other features tailored to how you use our services." | J8: 1 | K8: "We use automated systems that analyze your content to provide you with things like customized search results, personalized ads, or other features tailored to how you use our services." | L8: 1 | M8: Many websites and apps partner with Google to improve their content and services. For example, a website might use our advertising services (like AdSense) or analytics tools (like Google Analytics), or it might embed other content (such as videos from YouTube). These services may share information about your activity with Google and, depending on your account settings and the products in use (for instance, when a partner uses Google Analytics in conjunction with our advertising services), this data may be associated with your personal information | N8: 0 | O8: No mention in their privacy policy | P8: 1 | Q8: Buying, in this case | R8: 0 | U8: https://policies.google.com/privacy?hl=en&fg=1#infocollect | V8: =IF(ISNUMBER(SEARCH("Advertising", G8)), IF(L8 = 1, 1, 0), "") -> 1 | W8: =IF(ISNUMBER(SEARCH("Advertising", G8)), IF(H8 = 1, 1, 0), "") -> 1 | X8: =IF(ISNUMBER(SEARCH("Advertising", G8)), IF(J8 = 1, 1, 0), "") -> 1
A9: 21 | B9: https://www.justuno.com/ | C9: 45215 | D9: Oliver | E9: 45660 | F9: 1 | G9: Advertising | H9: 1 | I9: "we partner with third parties that collect information across various channels, including offline and online, for purposes of delivering more relevant advertising to you or your business" | J9: 0 | L9: 1 | M9: Justuno does not sell (as such term is defined in the CCPA) the personal information we collect (and will not sell it without providing a right to opt out). Please note that we do use third-party cookies for our advertising purposes as further described in our Cookie Policy. | N9: 0 | P9: 1 | R9: 0 | U9: https://www.justuno.com/legal/privacy-policy/ | V9: =IF(ISNUMBER(SEARCH("Advertising", G9)), IF(L9 = 1, 1, 0), "") -> 1 | W9: =IF(ISNUMBER(SEARCH("Advertising", G9)), IF(H9 = 1, 1, 0), "") -> 1 | X9: =IF(ISNUMBER(SEARCH("Advertising", G9)), IF(J9 = 1, 1, 0), "") -> 0
A10: 30 | B10: https://polen.com.br/ | C10: 45194 | D10: Sophie | E10: 45660 | F10: 1 | G10: Analytics | H10: 0 | J10: 0 | K10: Among the information collected by Polen is: Preferences information such as: products, cart history, order history. Personal information and data are not stored. | L10: 1 | M10: Eventually Polen may serve advertising of its products through Polen ... In some cases, third-party service providers may use cookies in Polen without the control of Polen. Such cookies are not regulated by this T&P, and the User must agree to the respective conditions of use of such third-party cookies. | N10: 0 | O10: The User has the option to accept or refuse the use of cookies on their computer, regardless of registration with Polen, by configuring their browser as desired. Refusal to use cookies may, however, result in limiting the User's access to certain tools available on Polen, difficulties in logging in and using Polen tools. | P10: 1 | Q10: Proof by existence of opt out | R10: 0 | U10: https://polen.com.br/termos-de-uso-e-politica-privacidade | V10: =IF(ISNUMBER(SEARCH("Advertising", G10)), IF(L10 = 1, 1, 0), "") | W10: =IF(ISNUMBER(SEARCH("Advertising", G10)), IF(H10 = 1, 1, 0), "") | X10: =IF(ISNUMBER(SEARCH("Advertising", G10)), IF(J10 = 1, 1, 0), "")
A11: 33 | B11: https://www.roq.ad/ | C11: 45194 | D11: Sophie | E11: 45660 | F11: 1 | G11: Advertising | H11: 0 | J11: 1 | K11: Inferences drawn from any of the information above to create a profile about a consumer reflecting the consumer’s preferences, characteristics, psychological trends, predispositions, behavior, attitudes, intelligence, abilities, and aptitudes. | L11: 1 | M11: If you do not want your information to be collected, you can choose to opt-out anytime on any of your digital devices. It is important to note that even if you opt-out, you will continue to see the same amount of advertising. The only difference will be that the ads themselves will not be as personalized or tailored and will appear more irrelevant to you. | N11: 1 | O11: This opt-out must be performed on each device and browser that you want to be opted out on. | P11: 1 | Q11: Proof by existence of opt out | R11: 0 | U11: https://www.roq.ad/white-papers/#optout | V11: =IF(ISNUMBER(SEARCH("Advertising", G11)), IF(L11 = 1, 1, 0), "") -> 1 | W11: =IF(ISNUMBER(SEARCH("Advertising", G11)), IF(H11 = 1, 1, 0), "") -> 0 | X11: =IF(ISNUMBER(SEARCH("Advertising", G11)), IF(J11 = 1, 1, 0), "") -> 1
A12: 36 | B12: https://www.socital.com | C12: 45194 | D12: Sophie | E12: 45660 | F12: 1 | G12: Advertising | H12: 1 | I12: to send you information about products and services (including our products and services and those of third parties) in which we believe you may be interested | J12: 1 | K12: The information that we may collect with these automated methods may include, for example, your IP address, cookie information, a unique device or user ID, browser type, system type, the content and pages that you access on the Socital Site or Services, the frequency and duration of your visits to the Socital Site or Services, and the “referring URL” | L12: 1 | M12: These other websites may place their own cookies or other files on your computer, collect data or solicit Personal Information from you. | N12: 0 | O12: You can configure your Internet browser, by changing its options, to stop accepting cookies completely or to prompt you before accepting a cookie from the website you visit | P12: 1 | Q12: Proof by existence of opt out | R12: 0 | U12: https://socital.com/privacy/ | V12: =IF(ISNUMBER(SEARCH("Advertising", G12)), IF(L12 = 1, 1, 0), "") -> 1 | W12: =IF(ISNUMBER(SEARCH("Advertising", G12)), IF(H12 = 1, 1, 0), "") -> 1 | X12: =IF(ISNUMBER(SEARCH("Advertising", G12)), IF(J12 = 1, 1, 0), "") -> 1
A13: 39 | B13: http://thetradedesk.com/ | C13: 45194 | D13: Oliver | E13: 45660 | F13: 1 | G13: Advertising | H13: 1 | I13: "Our Platform helps power ad targeting and delivery across many sites and apps with which users interact every day." | J13: 1 | K13: "As part of our Platform, we may create and use user profiles associated with pseudonymous identifiers." | L13: 1 | M13: By following the instructions below, you may request The Trade Desk limit its (a) use of your personal information for targeted advertising purposes and (b) sale or sharing of your personal information. | N13: 1 | O13: If you want to go directly to our Opt Out, please visit http://www.adsrvr.org. | P13: 1 | Q13: Proof by existence of opt out | R13: 1 | S13: TTDOptOut cookie | T13: trust arc optout method | U13: https://www.adsrvr.org/ | V13: =IF(ISNUMBER(SEARCH("Advertising", G13)), IF(L13 = 1, 1, 0), "") -> 1 | W13: =IF(ISNUMBER(SEARCH("Advertising", G13)), IF(H13 = 1, 1, 0), "") -> 1 | X13: =IF(ISNUMBER(SEARCH("Advertising", G13)), IF(J13 = 1, 1, 0), "") -> 1
A14: 42 | B14: https://yieldmo.com | C14: 45194 | D14: Oliver | E14: 45660 | F14: 1 | G14: Advertising | H14: 1 | I14: "The information collected pursuant to this Policy may be used to provide purchasing opportunities and aggregate reports to advertisers, agencies and publishers who participate in the Yieldmo Service, to schedule, deliver and optimize advertisements..." | J14: 1 | K14: "Collected information includes; cookie or mobile device identifiers, session length, IP address, location, time of usage, viewed pages and files, your advertising campaign selections, and other information regarding your use of the Website (collectively with Registration Data, the “Account Data”)." | L14: 1 | M14: Opt Out of Sales or Exercise Your “Do Not Sell My Personal Information” Right Under CCPA | N14: 1 | O14: "You can opt-out via Yieldmo’s opt-out tool here:" (https://yieldmo.com/opt-out/) | P14: 1 | Q14: Proof by existence of opt out | R14: 1 | S14: OPTOUT cookie | U14: https://yieldmo.com/privacy-policy/ | V14: =IF(ISNUMBER(SEARCH("Advertising", G14)), IF(L14 = 1, 1, 0), "") -> 1 | W14: =IF(ISNUMBER(SEARCH("Advertising", G14)), IF(H14 = 1, 1, 0), "") -> 1 | X14: =IF(ISNUMBER(SEARCH("Advertising", G14)), IF(J14 = 1, 1, 0), "") -> 1
B15: Total Sites | F15: Crosslisted | G15: Crosslisted with Advertising | H15: Targeted Advertising | J15: Profiling | L15: Selling | N15: Setting: To Opt Out | P15: Selling By Default | R15: Sign of not selling | V15: Total Crosslisted with Advertising + Selling | W15: Total Crosslisted with Advertising + Targeting | X15: Total Crosslisted with Advertising + Profiling
A16: Totals | B16: =COUNTIF(B1:B14,"<>") - 1 -> 13 | F16: =COUNTIF(F2:F14,"1") -> 13 | G16: =COUNTIF(G2:G14,"*Advertising*") -> 11 | H16: =COUNTIF(H2:H14,"1") -> 10 | J16: =COUNTIF(J2:J14,"1") -> 11 | L16: =COUNTIF(L2:L14,"1") -> 13 | N16: =COUNTIF(N2:N14,"1") -> 7 | P16: =COUNTIF(P2:P14,"1") -> 13 | R16: =COUNTIF(R2:R14,"1") -> 4 | V16: =SUM(V2:V14) -> 11 | W16: =SUM(W2:W14) -> 9 | X16: =SUM(X2:X14) -> 10

Sheet FingerprintInv
B1: Network URL [URL] | C1: Date of Analysis [DATE] | D1: Reviewer [Name] | E1: Date of Selling/Sharing (Buying/Collecting) Doublechecked by SZ [DATE] | F1: Crosslisted [0, 1] | G1: Crosslisted Category [Category Name] | H1: Targeted Advertising [0, 1] | I1: Evidence | J1: Profiling [0, 1] | K1: Evidence | L1: Selling/Sharing (Buying/Collecting) [0, 1] | M1: Evidence | N1: Setting: To Opt Out [0, 1] | O1: Evidence | P1: Selling By Default [0, 1] | Q1: Evidence | R1: Sign of Not Selling [0, 1] | S1: What is it [Name of Tag] | T1: Evidence | U1: Relevant URL [URL] | V1: Crosslisted with Advertising + Selling [0,1] | W1: Crosslisted with Advertising + Targeted Advertising [0,1] | X1: Crosslisted with Advertising + Profiling [0,1] | Y1: Crosslisted with FingerprintGen + Selling [0,1] | Z1: Crosslisted with FingerprintGen + Targeted Advertising [0,1] | AA1: Crosslisted with FingerprintGen + Profiling [0,1]
A2: 39 | B2: https://fingerprint.com/ | C2: 45194 | D2: Oliver | E2: N/A | F2: 1 | G2: Analytics | H2: 1 | I2: "We use this information to determine products and services that may be of interest to you for marketing purposes." | J2: 1 | K2: "We also collect personal data about you automatically when you use the Service... Approximate location information... Information about how you access and use the Service... Log files and information about your device" | L2: 1 | M2: "If FingerprintJS receives a request made pursuant to the CCPA directly from a Consumer with respect to Personal Information, then FingerprintJS shall either act on behalf of Customer or in accordance with Customer’s instructions in responding to the request or inform the Consumer that the request cannot be acted upon because the request has been sent to a Service Provider" Clearly subject to the CCPA | N2: 0 | O2: No mention | P2: 1 | Q2: Yes, by no mention of opt out | R2: 0 | U2: https://dev.fingerprint.com/docs/privacy-policy?_gl=1*h2f0uq*_ga*MjI0MzcwMTc1LjE2OTU2NzkxNDE.*_ga_XVKDT0L5WV*MTY5NTY3OTE0MC4xLjAuMTY5NTY3OTE0NC41Ni4wLjA. https://dev.fingerprint.com/docs/dpa-ccpa | V2: =IF(ISNUMBER(SEARCH("Advertising", G2)), IF(L2 = 1, 1, 0), "") | W2: =IF(ISNUMBER(SEARCH("Advertising", G2)), IF(H2 = 1, 1, 0), "") | X2: =IF(ISNUMBER(SEARCH("Advertising", G2)), IF(J2 = 1, 1, 0), "") | Y2: =IF(ISNUMBER(SEARCH("FingerprintGen", G2)), IF(L2 = 1, 1, 0), "") | Z2: =IF(ISNUMBER(SEARCH("FingerprintGen", G2)), IF(H2 = 1, 1, 0), "") | AA2: =IF(ISNUMBER(SEARCH("FingerprintGen", G2)), IF(J2 = 1, 1, 0), "")
A3: 46 | B3: https://hilltopads.com/ | C3: 45194 | D3: Oliver | E3: N/A | F3: 1 | G3: Advertising | H3: 1 | I3: "Information regarding Your Properties (including its URL, its category and other similar information) will be made available to other users of the Service for the purposes of selling advertising space or buying advertising space, as the case may be." | J3: 0 | K3: Does not explicitly mention information being automatically collected | L3: 1 | M3: "However, your information will be shared with other parties in the following situations: Information regarding Your Properties (including its URL, its category and other similar information) will be made available to other users of the Service for the purposes of selling advertising space or buying advertising space, as the case may be." | N3: 0 | O3: No mention | P3: 1 | Q3: Yes, by no mention of opt out | R3: 0 | U3: https://hilltopads.com/page/legal#privacypolicy | V3: =IF(ISNUMBER(SEARCH("Advertising", G3)), IF(L3 = 1, 1, 0), "") -> 1 | W3: =IF(ISNUMBER(SEARCH("Advertising", G3)), IF(H3 = 1, 1, 0), "") -> 1 | X3: =IF(ISNUMBER(SEARCH("Advertising", G3)), IF(J3 = 1, 1, 0), "") -> 0 | Y3: =IF(ISNUMBER(SEARCH("FingerprintGen", G3)), IF(L3 = 1, 1, 0), "") | Z3: =IF(ISNUMBER(SEARCH("FingerprintGen", G3)), IF(H3 = 1, 1, 0), "") | AA3: =IF(ISNUMBER(SEARCH("FingerprintGen", G3)), IF(J3 = 1, 1, 0), "")
A4: 52 | B4: https://www.imachines.com/ | C4: 45194 | D4: Oliver | E4: N/A | F4: 1 | G4: Anti-Fraud | H4: 1 | I4: "We generally use Cookies for the following purposes: To serve you with interest-based or targeted advertising." | J4: 0 | K4: Information collected automatically as a result of a Visitors or Users use of the Site or the Services ("Analytics Information"), such as IP addresses, browser type, Internet service provider, platform type, device type, operating system, date and time stamp of access, and other similar information. | L4: 0 | M4: Seems largely like an analytics site | N4: 0 | P4: 0 | R4: 0 | U4: https://www.imachines.com/privacy | V4: =IF(ISNUMBER(SEARCH("Advertising", G4)), IF(L4 = 1, 1, 0), "") | W4: =IF(ISNUMBER(SEARCH("Advertising", G4)), IF(H4 = 1, 1, 0), "") | X4: =IF(ISNUMBER(SEARCH("Advertising", G4)), IF(J4 = 1, 1, 0), "") | Y4: =IF(ISNUMBER(SEARCH("FingerprintGen", G4)), IF(L4 = 1, 1, 0), "") | Z4: =IF(ISNUMBER(SEARCH("FingerprintGen", G4)), IF(H4 = 1, 1, 0), "") | AA4: =IF(ISNUMBER(SEARCH("FingerprintGen", G4)), IF(J4 = 1, 1, 0), "")
A5: 66 | B5: https://www.maxmind.com/en/home | C5: 45194 | D5: Oliver | E5: N/A | F5: 1 | G5: Analytics | H5: 1 | I5: "Some databases may be used for marketing and advertising purposes for example to serve advertisements in a geographic area." | J5: 1 | K5: "The categories of information we automatically collect include: Device identifiers... Device information...Internet activity... Non-precise location data" | L5: 1 | M5: "Some of our disclosures of personal information may be considered a "sale" or "share" as those terms are defined under CPRA" | N5: 1 | O5: You also have the right to opt out of the processing of personal data for purposes of targeted advertising, or the sale of personal data. You can exercise these rights (i) by visiting by clicking Do Not Sell My Personal Information or (ii) by turning on a recognized opt-out preference signal, such as GPC in your browser or extension | P5: 1 | Q5: Proof by existence of opt out | R5: 0 | S5: Unclear | U5: https://www.maxmind.com/en/privacy-policy https://www.maxmind.com/en/opt-out | V5: =IF(ISNUMBER(SEARCH("Advertising", G5)), IF(L5 = 1, 1, 0), "") | W5: =IF(ISNUMBER(SEARCH("Advertising", G5)), IF(H5 = 1, 1, 0), "") | X5: =IF(ISNUMBER(SEARCH("Advertising", G5)), IF(J5 = 1, 1, 0), "") | Y5: =IF(ISNUMBER(SEARCH("FingerprintGen", G5)), IF(L5 = 1, 1, 0), "") | Z5: =IF(ISNUMBER(SEARCH("FingerprintGen", G5)), IF(H5 = 1, 1, 0), "") | AA5: =IF(ISNUMBER(SEARCH("FingerprintGen", G5)), IF(J5 = 1, 1, 0), "")
A6: 115 | B6: https://www.wideorbit.com/ | C6: 45194 | D6: Oliver | E6: N/A | F6: 1 | G6: Advertising | H6: 0 | I6: "We collect anonymous data for each user that is used to show the best possible advertisement at each page view on the internet." | J6: 0 | K6: "We collect certain aggregate and non-personal information when you visit this Web site. Aggregate and non-personal information does not relate to a single identifiable visitor." | L6: 1 | M6: "Analyzing Personal Information for business reporting and providing personalized services: To better understand your interests and preferences, so that we can personalize our interactions with you and provide you with information and/or offers tailored to your interests." | N6: 0? | O6: Offers method for opting out of anonymized targeted advertising "To opt out go to www.youronlinechoices.com" | P6: 0 | R6: 0 | U6: https://www.wideorbit.com/privacy/ | V6: =IF(ISNUMBER(SEARCH("Advertising", G6)), IF(L6 = 1, 1, 0), "") -> 1 | W6: =IF(ISNUMBER(SEARCH("Advertising", G6)), IF(H6 = 1, 1, 0), "") -> 0 | X6: =IF(ISNUMBER(SEARCH("Advertising", G6)), IF(J6 = 1, 1, 0), "") -> 0 | Y6: =IF(ISNUMBER(SEARCH("FingerprintGen", G6)), IF(L6 = 1, 1, 0), "") | Z6: =IF(ISNUMBER(SEARCH("FingerprintGen", G6)), IF(H6 = 1, 1, 0), "") | AA6: =IF(ISNUMBER(SEARCH("FingerprintGen", G6)), IF(J6 = 1, 1, 0), "")
A7: 31 | B7: http://www.clickyab.com | C7: 45194 | D7: Sophie | E7: N/A | F7: 0 | H7: 1 | I7: Through the use of cookies, anonymous information about your use of our websites and other websites will be used to provide more relevant adverts about goods and services of interest to you. | J7: 0 | L7: 1 | M7: Through the use of cookies, anonymous information about your use of our websites and other websites will be used to provide more relevant adverts about goods and services of interest to you. | N7: 0 | O7: You have the ability to prevent your computer from accepting cookies but, if you do, certain functionality on the website may be impaired. | P7: 0 | R7: 0 | U7: Site in Indian or other foreign language | V7: =IF(ISNUMBER(SEARCH("Advertising", G7)), IF(L7 = 1, 1, 0), "") | W7: =IF(ISNUMBER(SEARCH("Advertising", G7)), IF(H7 = 1, 1, 0), "") | X7: =IF(ISNUMBER(SEARCH("Advertising", G7)), IF(J7 = 1, 1, 0), "") | Y7: =IF(ISNUMBER(SEARCH("FingerprintGen", G7)), IF(L7 = 1, 1, 0), "") | Z7: =IF(ISNUMBER(SEARCH("FingerprintGen", G7)), IF(H7 = 1, 1, 0), "") | AA7: =IF(ISNUMBER(SEARCH("FingerprintGen", G7)), IF(J7 = 1, 1, 0), "")
A8: 50 | B8: https://impact.com/ | C8: 45194 | D8: Sophie | E8: N/A | F8: 1 | G8: Advertising | H8: 1 | I8: Impact may use your Personal Information to contact you with newsletters, marketing or promotional materials and other information that may be of interest to you | J8: 1 | K8: Such Client Personal Information will include, but is not limited to, name, postal address, business email address, phone number and employer. | L8: 1 | M8: Service-related services and/or to assist us in analyzing how our Services are used. Examples may include ... providing marketing assistance, supplementing the information you provide us in order to provide you with better service, and providing customer service. | N8: 1 | O8: You may opt out of receiving any, or all, of these communications from us by following the unsubscribe link or instructions provided in any email we send. | P8: 1 | Q8: Proof by existence of opt out | R8: 0 | U8: https://impact.com/privacy-policy/ | V8: =IF(ISNUMBER(SEARCH("Advertising", G8)), IF(L8 = 1, 1, 0), "") -> 1 | W8: =IF(ISNUMBER(SEARCH("Advertising", G8)), IF(H8 = 1, 1, 0), "") -> 1 | X8: =IF(ISNUMBER(SEARCH("Advertising", G8)), IF(J8 = 1, 1, 0), "") -> 1 | Y8: =IF(ISNUMBER(SEARCH("FingerprintGen", G8)), IF(L8 = 1, 1, 0), "") | Z8: =IF(ISNUMBER(SEARCH("FingerprintGen", G8)), IF(H8 = 1, 1, 0), "") | AA8: =IF(ISNUMBER(SEARCH("FingerprintGen", G8)), IF(J8 = 1, 1, 0), "")
A9: 53 | B9: http://islay.tech | C9: 45194 | D9: Sophie | E9: N/A | F9: 1 | G9: Analytics | H9: 0 | J9: 1 | K9: Additionally, the website collects anonymous data regarding visited pages such as number of visits, country, browser, visit duration etc. | L9: 0 | N9: 0 | O9: The user has the option to block certain types of cookies and other technologies in their browser, for example, by specifying that only those necessary for the correct display of the page are allowed. | P9: 0 | R9: 0 | U9: https://islay.tech/en/privacy-policy/ | V9: =IF(ISNUMBER(SEARCH("Advertising", G9)), IF(L9 = 1, 1, 0), "") | W9: =IF(ISNUMBER(SEARCH("Advertising", G9)), IF(H9 = 1, 1, 0), "") | X9: =IF(ISNUMBER(SEARCH("Advertising", G9)), IF(J9 = 1, 1, 0), "") | Y9: =IF(ISNUMBER(SEARCH("FingerprintGen", G9)), IF(L9 = 1, 1, 0), "") | Z9: =IF(ISNUMBER(SEARCH("FingerprintGen", G9)), IF(H9 = 1, 1, 0), "") | AA9: =IF(ISNUMBER(SEARCH("FingerprintGen", G9)), IF(J9 = 1, 1, 0), "")
A10: 89 | B10: https://sendpulse.com/ | C10: 45194 | D10: Sophie | E10: N/A | F10: 1 | G10: Email, Analytics | H10: 1 | I10: We partner with third parties to display advertising on our website or to manage and serve our advertising on other sites. Our third party partners may use cookies or similar tracking technologies in order to provide you advertising or other content based upon your browsing activities and interests. | J10: 1 | K10: That data may include your or your Subscribers name, email address, physical address, IP address, phone number, age | L10: 1 | M10: We partner with third parties to display advertising on our website or to manage and serve our advertising on other sites. Our third party partners may use cookies or similar tracking technologies in order to provide you advertising or other content based upon your browsing activities and interests. | N10: 0 | O10: You may be able to change the preferences on your browser or device to prevent or limit your device’s acceptance of cookies, but this may prevent you from taking advantage of some of our features. | P10: 1 | Q10: you are responsible for making sure you have the appropriate permission for us to collect and process information about those individuals (explicit consent). Consent must be specific to your purposes. Silence, pre-ticked boxes or inactivity does not constitute consent; data subjects must explicitly opt-in to the storage, use and management of their personal data. | R10: 0 | U10: https://sendpulse.com/legal/pp | V10: =IF(ISNUMBER(SEARCH("Advertising", G10)), IF(L10 = 1, 1, 0), "") | W10: =IF(ISNUMBER(SEARCH("Advertising", G10)), IF(H10 = 1, 1, 0), "") | X10: =IF(ISNUMBER(SEARCH("Advertising", G10)), IF(J10 = 1, 1, 0), "") | Y10: =IF(ISNUMBER(SEARCH("FingerprintGen", G10)), IF(L10 = 1, 1, 0), "") | Z10: =IF(ISNUMBER(SEARCH("FingerprintGen", G10)), IF(H10 = 1, 1, 0), "") | AA10: =IF(ISNUMBER(SEARCH("FingerprintGen", G10)), IF(J10 = 1, 1, 0), "")
B12: Total Sites | F12: Crosslisted | G12: Crosslisted with Advertising | H12: Targeted Advertising | J12: Profiling | L12: Selling | N12: Setting: To Opt Out | P12: Selling By Default | R12: Sign of not selling | V12: Total Crosslisted with Advertising + Selling | W12: Total Crosslisted with Advertising + Targeting | X12: Total Crosslisted with Advertising + Profiling | Y12: Total Crosslisted with FingerprintGen + Selling | Z12: Total Crosslisted with FingerprintGen + Targeting | AA12: Total Crosslisted with FingerprintGen + Profiling
A13: Totals | B13: =COUNTIF(B1:B10,"<>") - 1 -> 9 | F13: =COUNTIF(F1:F10,"1") -> 8 | G13: =COUNTIF(G2:G10,"*Advertising*") -> 3 | H13: =COUNTIF(H1:H10,"1") -> 7 | J13: =COUNTIF(J1:J10,"1") -> 5 | L13: =COUNTIF(L1:L10,"1") -> 7 | N13: =COUNTIF(N1:N10,"1") -> 2 | P13: =COUNTIF(P1:P10,"1") -> 5 | R13: =COUNTIF(R1:R10,"1") -> 0 | V13: =SUM(V2:V10) -> 3 | W13: =SUM(W2:W10) -> 2 | X13: =SUM(X2:X10) -> 1 | Y13: =SUM(Y2:Y10) -> 0 | Z13: =SUM(Z2:Z10) -> 0 | AA13: =SUM(AA2:AA10) -> 0

Sheet Social
A1: ID | B1: Network URL [URL] | C1: Date of Analysis [DATE] | D1: Reviewer [Name] | E1: Date of Selling/Sharing (Buying/Collecting) Doublechecked by SZ [DATE] | F1: Crosslisted [0, 1] | G1: Crosslisted Category [Category Name] | H1: Targeted Advertising [0, 1] | I1: Evidence | J1: Profiling [0, 1] | K1: Evidence | L1: Sharing/Selling (Buying/Collecting) [0, 1] | M1: Evidence | N1: Setting: To Opt Out [0, 1] | O1: Evidence | P1: Selling By Default [0, 1] | Q1: Evidence | R1: Sign of Not Selling [0, 1] | S1: What is it [Name of Tag] | T1: Evidence | U1: Relevant URL [URL] | V1: Crosslisted with Advertising + Selling [0,1] | W1: Crosslisted with Advertising + Targeted Advertising [0,1] | X1: Crosslisted with Advertising + Profiling [0,1] | Y1: Crosslisted with FingerprintGen + Selling [0,1] | Z1: Crosslisted with FingerprintGen + Targeted Advertising [0,1] | AA1: Crosslisted with FingerprintGen + Profiling [0,1]
A2: 1 | B2: http://digg.com/ | C2: 45194 | D2: Sophie | E2: 45660 | F2: 0 | H2: 1 | I2: Digg may also use cookies to display the most appropriate advertisements, based on your interests and activity on our sites. | J2: 1 | K2: Each access is tracked using a unique identifier assigned to you in one or more cookies stored by your web browser or application and associated with Digg. Digg cookies do not, by themselves, contain Personal Data, and we do not combine the general information collected through cookies with other Personal Data to tell us who you are. | L2: 1 | M2: In connection with your use of Digg, we receive information about you from various sources, including: (i) through your Digg user account; (ii) your use of Digg generally; and (iii) from third-party websites and services. ... We may use pixel tags, either provided by us or by our third-party advertisers, service providers, and ad networks to collect information about your visit, including the pages you view, the links you click, and other actions taken in connection with Digg | N2: 0 | O2: For example, you may manage the use and collection of certain information by Google Analytics via the Google Analytics Opt-out Browser Add-on. | P2: 1 | Q2: We may otherwise collect information about how you are using Digg to interact with those connected Third-Party Services. | R2: 0 | U2: https://digg.com/privacy | V2: =IF(ISNUMBER(SEARCH("Advertising", G2)), IF(L2 = 1, 1, 0), "") | W2: =IF(ISNUMBER(SEARCH("Advertising", G2)), IF(H2 = 1, 1, 0), "") | X2: =IF(ISNUMBER(SEARCH("Advertising", G2)), IF(J2 = 1, 1, 0), "") | Y2: =IF(ISNUMBER(SEARCH("FingerprintGen", G2)), IF(L2 = 1, 1, 0), "") | Z2: =IF(ISNUMBER(SEARCH("FingerprintGen", G2)), IF(H2 = 1, 1, 0), "") | AA2: =IF(ISNUMBER(SEARCH("FingerprintGen", G2)), IF(J2 = 1, 1, 0), "")
A3: 2 | B3: https://www.facebook.com/ | C3: 45194 | D3: Oliver | E3: 45660 | F3: 1 | G3: Advertising Content FingerprintGen | H3: 1 | I3: "Why and how we process your information: Providing ads on the Meta Products: Our systems automatically process limited categories of information that we've collected and stored to provide you with ads on the Meta Products in accordance with our terms." | J3: 1 | K3: "Our systems automatically process information we collect and store associated with you and others to assess and understand your interests and your preferences and provide you personalized experiences across the Meta Products in accordance with our terms." | L3: 1 | M3: We collect and receive information from partners, measuring vendors, marketing vendors and other third parties about a variety of your information and activities on and off our Products. | N3: 1 | O3: "Cookie-based opt out: If applicable and available in your jurisdiction, you may use the DAA industry opt-out platform, available in English and Spanish. Residents of Canada may use the DAAoC industry opt-out platform. If you apply certain ad blockers and tools to restrict cookies, it may interfere with your ability to opt out. Mobile phone-based opt out: Check your mobile device settings. Different manufacturers provide different ways to opt out of advertisements. Other online identifiers: You may use the NAI industry opt-out platform." | P3: 1 | Q3: Proof by existence of optout | R3: 0 | S3: Unclear | U3: https://www.facebook.com/privacy/policy | V3: =IF(ISNUMBER(SEARCH("Advertising", G3)), IF(L3 = 1, 1, 0), "") -> 1 | W3: =IF(ISNUMBER(SEARCH("Advertising", G3)), IF(H3 = 1, 1, 0), "") -> 1 | X3: =IF(ISNUMBER(SEARCH("Advertising", G3)), IF(J3 = 1, 1, 0), "") -> 1 | Y3: =IF(ISNUMBER(SEARCH("FingerprintGen", G3)), IF(L3 = 1, 1, 0), "") -> 1 | Z3: =IF(ISNUMBER(SEARCH("FingerprintGen", G3)), IF(H3 = 1, 1, 0), "") -> 1 | AA3: =IF(ISNUMBER(SEARCH("FingerprintGen", G3)), IF(J3 = 1, 1, 0), "") -> 1
A4: 7 | B4: http://www.microsoft.com/ | C4: 45194 | D4: Oliver | E4: 45660 | F4: 1 | G4: Advertising Content Analytics FingerprintGen | H4: 1 | I4: "In particular, we use data to: ... Advertise and market to you, which includes sending promotional communications, targeting advertising, and presenting you with relevant offers." | J4: 1 | K4: "Data about your use of Microsoft products. In some cases, such as search queries, this is data you provide in order to make use of the products. In other cases, such as error reports, this is data we generate. Other examples of interactions data include: Interests and favorites Content consumption data..." Etc | L4: 1 | M4: We may “share” your personal data, as defined under California and other applicable U.S. state laws, for personalized advertising purposes | N4: 1 | O4: "Control the use of your data for personalized advertising from Microsoft by visiting our opt-out page." https://go.microsoft.com/fwlink/?LinkID=286759 | P4: 1 | Q4: Proof by existence of optout | R4: 0 | S4: Unclear | U4: https://privacy.microsoft.com/en-us/privacystatement https://go.microsoft.com/fwlink/?LinkID=286759 https://privacy.microsoft.com/en-US/ccpa | V4: =IF(ISNUMBER(SEARCH("Advertising", G4)), IF(L4 = 1, 1, 0), "") -> 1 | W4: =IF(ISNUMBER(SEARCH("Advertising", G4)), IF(H4 = 1, 1, 0), "") -> 1 | X4: =IF(ISNUMBER(SEARCH("Advertising", G4)), IF(J4 = 1, 1, 0), "") -> 1 | Y4: =IF(ISNUMBER(SEARCH("FingerprintGen", G4)), IF(L4 = 1, 1, 0), "") -> 1 | Z4: =IF(ISNUMBER(SEARCH("FingerprintGen", G4)), IF(H4 = 1, 1, 0), "") -> 1 | AA4: =IF(ISNUMBER(SEARCH("FingerprintGen", G4)), IF(J4 = 1, 1, 0), "") -> 1
A5: 8 | B5: http://www.oracle.com/ | C5: 45195 | D5: Sophie | E5: 45660 | F5: 1 | G5: Advertising, Analytics, Content | H5: 1 | I5: to provide Advertising services to Oracle customers and partners designed to enable them to market products and services to you based on your interests | J5: 1 | K5: We may associate personal information about you with interest segments or profiles as part of the provision of Oracle Advertising services to our customers and partners: | L5: 1 | M5: Under the California Consumer Privacy Act (CCPA), as amended, California residents may request that we: 1. disclose to you the following information: the categories and specific pieces of personal information we collected about you and the categories of personal information we sold (see Section 4); ... the categories of third parties to whom we sold or otherwise disclosed personal information (see Section 8). | N5: 1 | O5: You can opt out of cookies using the opt-out tools in the next section. | P5: 1 | Q5: Proof by existence of optout | R5: 1 | S5: Some cookie, unclear | U5: https://www.oracle.com/legal/privacy/privacy-choices.html | V5: =IF(ISNUMBER(SEARCH("Advertising", G5)), IF(L5 = 1, 1, 0), "") -> 1 | W5: =IF(ISNUMBER(SEARCH("Advertising", G5)), IF(H5 = 1, 1, 0), "") -> 1 | X5: =IF(ISNUMBER(SEARCH("Advertising", G5)), IF(J5 = 1, 1, 0), "") -> 1 | Y5: =IF(ISNUMBER(SEARCH("FingerprintGen", G5)), IF(L5 = 1, 1, 0), "") | Z5: =IF(ISNUMBER(SEARCH("FingerprintGen", G5)), IF(H5 = 1, 1, 0), "") | AA5: =IF(ISNUMBER(SEARCH("FingerprintGen", G5)), IF(J5 = 1, 1, 0), "")
A6: 10 | B6: http://www.reddit.com/ | C6: 45195 | D6: Sophie | E6: 45660 | F6: 0 | H6: 1 | I6: We use this information to deliver and maintain our services and our site, improve your experience, understand user activity, personalize content and advertisements, measure the effectiveness of advertising, and improve the quality of our Services. | J6: 1 | K6: We may log information when you access and use the Services. | L6: 1 | M6: We may receive information about you from other sources, including from other users and third parties, and combine that information with the other information we have about you. For example, we may receive demographic or interest information about you from third parties, including advertisers ... Reddit does not "sell” or "share” personal information as those terms are defined under the CCPA. We do not use or disclose sensitive personal information except to provide you the Services or as otherwise permitted by the CCPA. | N6: 1 | O6: You may opt out of us using information we collect from third parties, including advertising partners, to personalize the ads you see on Reddit. | P6: 1 | Q6: Proof by existence of optout | R6: 1 | S6: Behind firewall | U6: https://www.reddit.com/en-us/policies/privacy-policy-revision-2023-07-31 | V6: =IF(ISNUMBER(SEARCH("Advertising", G6)), IF(L6 = 1, 1, 0), "") | W6: =IF(ISNUMBER(SEARCH("Advertising", G6)), IF(H6 = 1, 1, 0), "") | X6: =IF(ISNUMBER(SEARCH("Advertising", G6)), IF(J6 = 1, 1, 0), "") | Y6: =IF(ISNUMBER(SEARCH("FingerprintGen", G6)), IF(L6 = 1, 1, 0), "") | Z6: =IF(ISNUMBER(SEARCH("FingerprintGen", G6)), IF(H6 = 1, 1, 0), "") | AA6: =IF(ISNUMBER(SEARCH("FingerprintGen", G6)), IF(J6 = 1, 1, 0), "")
A7: 11 | B7: http://www.shareaholic.com/ | C7: 45195 | D7: Sophie | E7: 45660 | F7: 0 | H7: 1 | I7: Shareaholic may also use other third-party cookies to track the performance of Company advertisements or to assist advertisers in delivering a more relevant advertising experience. | J7: 1 | K7: "Personal information" is information that you provide to us which personally identifies you, such as your name, email address, or other data which can be reasonably linked to such information by Shareaholic. | L7: 1 | M7: This is accomplished by providing information about visitors to third-parties with whom we have a relationship. These partners may collect information such as, but not limited to, which web page you came from, which type of browser you are using, and your geographic location, or that you have expressed interest in a website’s content. | N7: 1 | O7: If however, you prefer that we do not use cookies to collect information about your browsing pattern for the purpose of delivering targeted advertising, you may opt out at any time by clicking on our "Opt-Out" link here. | P7: 1 | Q7: Proof by existence of optout | R7: 1 | S7: opt_out | U7: https://www.shareaholic.com/privacy/ | V7: =IF(ISNUMBER(SEARCH("Advertising", G7)), IF(L7 = 1, 1, 0), "") | W7: =IF(ISNUMBER(SEARCH("Advertising", G7)), IF(H7 = 1, 1, 0), "") | X7: =IF(ISNUMBER(SEARCH("Advertising", G7)), IF(J7 = 1, 1, 0), "") | Y7: =IF(ISNUMBER(SEARCH("FingerprintGen", G7)), IF(L7 = 1, 1, 0), "") | Z7: =IF(ISNUMBER(SEARCH("FingerprintGen", G7)), IF(H7 = 1, 1, 0), "") | AA7: =IF(ISNUMBER(SEARCH("FingerprintGen", G7)), IF(J7 = 1, 1, 0), "")
A8: 12 | B8: http://sharethis.com/ | C8: 45194 | D8: Oliver | E8: 45660 | F8: 0 | H8: 1 | I8: "We compile this data and provide it to our Publishers and license it to advertisers, agencies, and other businesses (our “Customers”) to facilitate the delivery of relevant, targeted advertising and for a number of other reasons which are listed below." | J8: 1 | K8: "We use cookies and similar tracking technologies to collect data automatically when you visit ShareThis.com and use that information to help administer the Website, to remember your preferences, to conduct website analytics and for security and fraud prevention purposes. " | L8: 1 | M8: Where we enable third parties to collect pseudonymous information on ShareThis.com (e.g., using cookies and pixels), that information may be viewed as a sale of data by ShareThis under applicable in certain jurisdictions such as California. | N8: 1 | O8: "If you do not want to receive advertisements based on Usage Data and Profile Information collected by ShareThis on your current browser, you can change and manage your preferences in relation to the collection and processing of Usage Data and Profile Information by clicking the ShareThis opt-out button available on this privacy policy." | P8: 1 | Q8: Proof by existence of optout | R8: 1 | S8: st_optout cookie | U8: https://sharethis.com/privacy/ | V8: =IF(ISNUMBER(SEARCH("Advertising", G8)), IF(L8 = 1, 1, 0), "") | W8: =IF(ISNUMBER(SEARCH("Advertising", G8)), IF(H8 = 1, 1, 0), "") | X8: =IF(ISNUMBER(SEARCH("Advertising", G8)), IF(J8 = 1, 1, 0), "") | Y8: =IF(ISNUMBER(SEARCH("FingerprintGen", G8)), IF(L8 = 1, 1, 0), "") | Z8: =IF(ISNUMBER(SEARCH("FingerprintGen", G8)), IF(H8 = 1, 1, 0), "") | AA8: =IF(ISNUMBER(SEARCH("FingerprintGen", G8)), IF(J8 = 1, 1, 0), "")
A9: 13 | B9: http://www.snap.com/ | C9: 45195 | D9: Sophie | E9: 45660 | F9: 1 | G9: Advertising | H9: 1 | I9: We may obtain information from advertisers, app developers, publishers, and other third parties. We may use this information, among other ways, to help target or measure the performance of ads. | J9: 1 | K9: When you use our services, you may engage with the camera or creative tools and create and share various types of content including Stories, Snaps, and more. We collect information about content you create or provide on our services, and your engagement with the camera and creative tools. | L9: 1 | M9: For example, we may use information collected on other websites to show you more relevant ads | N9: 0 | P9: 1 | Q9: Most web browsers are set to accept cookies by default. | R9: 0 | T9: Your browser may provide you with the option to refuse some or all non-essential browser cookies. | U9: https://values.snap.com/privacy/privacy-policy | V9: =IF(ISNUMBER(SEARCH("Advertising", G9)), IF(L9 = 1, 1, 0), "") -> 1 | W9: =IF(ISNUMBER(SEARCH("Advertising", G9)), IF(H9 = 1, 1, 0), "") -> 1 | X9: =IF(ISNUMBER(SEARCH("Advertising", G9)), IF(J9 = 1, 1, 0), "") -> 1 | Y9: =IF(ISNUMBER(SEARCH("FingerprintGen", G9)), IF(L9 = 1, 1, 0), "") | Z9: =IF(ISNUMBER(SEARCH("FingerprintGen", G9)), IF(H9 = 1, 1, 0), "") | AA9: =IF(ISNUMBER(SEARCH("FingerprintGen", G9)), IF(J9 = 1, 1, 0), "")
A10: 15 | B10: https://www.tiktok.com/ | C10: 45194 | D10: Oliver | E10: 45660 | F10: 1 | G10: Advertising | H10: 1 | I10: "To measure and understand the effectiveness of the advertisements we serve to you and others and to deliver advertising, including targeted advertising, to you on the Platform." | J10: 1 | K10: "We automatically collect certain information from you when you use the Platform, including internet or other network activity information such as your IP address, geolocation-related data, unique device identifiers, browsing and search history (including content you have viewed in the Platform), and Cookies." | L10: 1 | M10: Advertisers, measurement and other partners share information with us about you and the actions you have taken outside of the Platform, such as your activities on other websites and apps or in stores, including the products or services you purchased, online or in person. These partners also share information with us, such as mobile identifiers for advertising, hashed email addresses and phone numbers, and cookie identifiers, which we use to help match you and your actions outside of the Platform with your TikTok account. Some of our advertisers and other partners enable us to collect similar information directly from their websites or apps by integrating our TikTok Advertiser Tools (such as TikTok Pixel). ... We are committed to maintaining your trust, and while TikTok does not sell your personal information or share your personal information with third parties for purposes of cross-context behavioral advertising where restricted by applicable law, we want you to understand when and with whom we may share the Information We Collect for business purposes. | N10: 1 | O10: "You can navigate to "Ads" in your in-app settings to opt-out of targeted advertising based on personal information about your activity on nonaffiliated apps and websites." | P10: 0 | R10: 0 | S10: Unclear | U10: https://www.tiktok.com/legal/page/us/privacy-policy/en | V10: =IF(ISNUMBER(SEARCH("Advertising", G10)), IF(L10 = 1, 1, 0), "") -> 1 | W10: =IF(ISNUMBER(SEARCH("Advertising", G10)), IF(H10 = 1, 1, 0), "") -> 1 | X10: =IF(ISNUMBER(SEARCH("Advertising", G10)), IF(J10 = 1, 1, 0), "") -> 1 | Y10: =IF(ISNUMBER(SEARCH("FingerprintGen", G10)), IF(L10 = 1, 1, 0), "") | Z10: =IF(ISNUMBER(SEARCH("FingerprintGen", G10)), IF(H10 = 1, 1, 0), "") | AA10: =IF(ISNUMBER(SEARCH("FingerprintGen", G10)), IF(J10 = 1, 1, 0), "")
A11: 18 | B11: http://www.yahoo.com/ | C11: 45194 | D11: Oliver | E11: 45660 | F11: 1 | G11: Advertising Content Analytics | H11: 1 | I11: "Match and serve targeted advertising (across devices and both on and off of our Services) and provide targeted advertising based on your device activity, inferred interests and location information." | J11: 1 | K11: "We collect information when you access content, advertising, sites, interactive widgets, applications, and other products (both on and off of our Services) where Yahoo data collection technologies (such as web beacons, development tools, cookies and other technologies, etc.) are present." | L11: 1 | M11: We do not sell, license or share information that individually identifies our customers with companies, organizations or individuals outside of Yahoo unless one of the following circumstances applies: ... Advertising, Analytics and Business Partners (Limited to Non-Personally Identifiable Information). We may share aggregated or pseudonymous information (including demographic information) with partners, such as publishers, advertisers, measurement analytics, apps, or other companies. For example, we may tell an advertiser how its ads performed or report how many people installed an app after seeing a promotion. | N11: 1 | O11: "For example, you can review or edit your account information, manage your marketing preferences, or opt out of targeted ads." | P11: 1 | Q11: Proof by existence of optout | R11: 0 | S11: Unclear | T11: Very nice opt-out tool | U11: https://legal.yahoo.com/us/en/yahoo/privacy/dashboard/index.html https://legal.yahoo.com/us/en/yahoo/privacy/index.html | V11: =IF(ISNUMBER(SEARCH("Advertising", G11)), IF(L11 = 1, 1, 0), "") -> 1 | W11: =IF(ISNUMBER(SEARCH("Advertising", G11)), IF(H11 = 1, 1, 0), "") -> 1 | X11: =IF(ISNUMBER(SEARCH("Advertising", G11)), IF(J11 = 1, 1, 0), "") -> 1 | Y11: =IF(ISNUMBER(SEARCH("FingerprintGen", G11)), IF(L11 = 1, 1, 0), "") | Z11: =IF(ISNUMBER(SEARCH("FingerprintGen", G11)), IF(H11 = 1, 1, 0), "") | AA11: =IF(ISNUMBER(SEARCH("FingerprintGen", G11)), IF(J11 = 1, 1, 0), "")
B13: Total Sites | F13: Crosslisted | G13: Crosslisted with Advertising | H13: Targeted Advertising | J13: Profiling | L13: Selling | N13: Setting: To Opt Out | P13: Selling By Default | R13: Sign of not selling | V13: Total Crosslisted with Advertising + Selling | W13: Total Crosslisted with Advertising + Targeting | X13: Total Crosslisted with Advertising + Profiling | Y13: Total Crosslisted with FingerprintGen + Selling | Z13: Total Crosslisted with FingerprintGen + Targeting | AA13: Total Crosslisted with FingerprintGen + Profiling
A14: Totals | B14: =COUNTIF(B1:B11,"<>") - 1 -> 10 | F14: =COUNTIF(F2:F11,"1") -> 6 | G14: =COUNTIF(G2:G11,"*Advertising*") -> 6 | H14: =COUNTIF(H2:H11,"1") -> 10 | J14: =COUNTIF(J2:J11,"1") -> 10 | L14: =COUNTIF(L2:L11,"1") -> 10 | N14: =COUNTIF(N2:N11,"1") -> 8 | P14: =COUNTIF(P2:P11,"1") -> 9 | R14: =COUNTIF(R2:R11,"1") -> 4 | V14: =SUM(V2:V11) -> 6 | W14: =SUM(W2:W11) -> 6 | X14: =SUM(X2:X11) -> 6 | Y14: =SUM(Y2:Y11) -> 2 | Z14: =SUM(Z2:Z11) -> 2 | AA14: =SUM(AA2:AA11) -> 2

Sheet Results
A1: Results | B1: Total # of Sites | C1: # of Targeted Advertising | D1: # of Profiling | E1: # of Selling/Sharing | F1: # Crosslisted with Adv. | G1: % selling/sharing
A2: Advertising | B2: =COUNTIF(Advertising!L2:L71,"<>N/A") -> 68 | C2: =COUNTIF(Advertising!H2:H71,"1") -> 65 | D2: =COUNTIF(Advertising!J2:J71,"1") -> 61 | E2: =COUNTIF(Advertising!L2:L71,"1") -> 63 | F2: =SUM(Advertising!B73) -> 70 | G2: =$E2/$B2 -> 0.92647059
A3: Analytics | B3: =COUNTIF(Analytics!B2:B16,"<>") -> 15 | C3: =COUNTIF(Analytics!H2:H16,"1") -> 11 | D3: =COUNTIF(Analytics!J2:J16,"1") -> 12 | E3: =COUNTIF(Analytics!L2:L16,"1") -> 8 | F3: =SUM(Analytics!G18) -> 2 | G3: =$E3/$B3 -> 0.53333333
A4: FingerprintGen | B4: =COUNTIF(FingerprintGen!B2:B14,"<>") -> 13 | C4: =COUNTIF(FingerprintGen!H2:H14,"1") -> 10 | D4: =COUNTIF(FingerprintGen!J2:J14,"1") -> 11 | E4: =COUNTIF(FingerprintGen!L2:L14,"1") -> 13 | F4: =SUM(FingerprintGen!G16) -> 11 | G4: =$E4/$B4 -> 1
A5: FingerprintInv | B5: =COUNTIF(FingerprintInv!B2:B10,"<>") -> 9 | C5: =COUNTIF(FingerprintInv!H2:H10,"1") -> 7 | D5: =COUNTIF(FingerprintInv!J2:J10,"1") -> 5 | E5: =COUNTIF(FingerprintInv!L2:L10,"1") -> 7 | F5: =SUM(FingerprintInv!G13) -> 3 | G5: =$E5/$B5 -> 0.77777778
A6: Social | B6: =COUNTIF(Social!B2:B11,"<>") -> 10 | C6: =COUNTIF(Social!H2:H11,"1") -> 10 | D6: =COUNTIF(Social!J2:J11,"1") -> 10 | E6: =COUNTIF(Social!L2:L11,"1") -> 10 | F6: =SUM(Social!G11) -> 0 | G6: =$E6/$B6 -> 1
A7: Total | B7: =SUM(B2:B6) -> 115 | C7: =SUM(C2:C6) -> 103 | D7: =SUM(D2:D6) -> 99 | E7: =SUM(E2:E6) -> 101 | F7: =SUM(F2:F6) -> 86 | G7: =$E7/$B7 -> 0.87826087
A10: Percentages | B10: =B1 -> Total # of Sites | C10: % of Targeted Advertising | D10: % of Profiling | E10: % of Selling/Sharing | F10: % Crosslisted with Adv. | G10: % Adv. + Selling
A11: Advertising | B11: =B2 -> 68 | C11: =round(C2/B2,2) -> 0.96 | D11: =round(D2/B2,2) -> 0.9 | E11: =round(E2/B2,2) -> 0.93 | F11: =round(F2/B2,2) -> 1.03 | G11: =round(G2/B2,2) -> 0.01
A12: Analytics | B12: =B3 -> 15 | C12: =round(C3/B3,2) -> 0.73 | D12: =round(D3/B3,2) -> 0.8 | E12: =round(E3/B3,2) -> 0.53 | F12: =round(F3/B3,2) -> 0.13 | G12: =round(G3/B3,2) -> 0.04
A13: FingerprintGen | B13: =B4 -> 13 | C13: =round(C4/B4,2) -> 0.77 | D13: =round(D4/B4,2) -> 0.85 | E13: =round(E4/B4,2) -> 1 | F13: =round(F4/B4,2) -> 0.85 | G13: =round(G4/B4,2) -> 0.08
A14: FingerprintInv | B14: =B5 -> 9 | C14: =round(C5/B5,2) -> 0.78 | D14: =round(D5/B5,2) -> 0.56 | E14: =round(E5/B5,2) -> 0.78 | F14: =round(F5/B5,2) -> 0.33 | G14: =round(G5/B5,2) -> 0.09
A15: Social | B15: =B6 -> 10 | C15: =round(C6/B6,2) -> 1 | D15: =round(D6/B6,2) -> 1 | E15: =round(E6/B6,2) -> 1 | F15: =round(F6/B6,2) -> 0 | G15: =round(G6/B6,2) -> 0.1
A18: Percentages by Category Union | B18: Total # of Sites | C18: % of Targeted Advertising | D18: % of Profiling | E18: % of Selling/Sharing
A19: Advertising + FingerprintGen + Social | B19: =SUM(B2,Analytics!G18,FingerprintGen!B16,FingerprintInv!G13,Social!B14,Analytics!G20) -> 97 | C19: =ROUND(SUM(Analytics!W18, Advertising!H73, FingerprintGen!H16,FingerprintInv!W13,Social!H14,Analytics!Z18)/B19,2) -> 0.93 | D19: =ROUND(SUM(Advertising!J73,Analytics!X18,FingerprintGen!J16,FingerprintInv!X13,Social!J14,Analytics!AA18)/B19,2) -> 0.89 | E19: =ROUND(SUM(Advertising!L73,Analytics!V18,FingerprintGen!L16,FingerprintInv!V13,Social!L14,Analytics!Y18)/B19,2) -> 0.95
A22: Standard Error | B22: % of Targeted Advertising | C22: % of Profiling | D22: % of Selling/Sharing
A23: Advertising + FingerprintGen + Social | B23: =SQRT(C19*(1-C19)/B19) -> 0.025906254 | C23: =SQRT(D19*(1-D19)/B19) -> 0.031769141 | D23: =SQRT(E19*(1-E19)/B19) -> 0.022128957
A26: Confidence Interval Ranges (95%) | B26: Targeted Advertising | D26: Profiling | F26: Selling / Sharing
B27: Min | C27: Max | D27: Min | E27: Max | F27: Min | G27: Max
A28: Advertising + FingerprintGen + Social | B28: =SUM(C19-B23*1.96) -> 0.87922374 | C28: =SUM(C19+B23*1.96) -> 0.98077626 | D28: =SUM(D19-C23*1.96) -> 0.82773248 | E28: =SUM(D19+C23*1.96) -> 0.95226752 | F28: =SUM(E19-D23*1.96) -> 0.90662725 | G28: =SUM(E19+D23*1.96) -> 0.99337275
A30: half interval width | B30: 0.05
A32: # sites needed to get 95% confidence interval with half width < above # | B32: targeted advertising | C32: profiling | D32: selling/sharing
A33: Advertising + FingerprintGen + Social | B33: =((1/($B$30))^2)*C19*(1-C19)*(1.96)^2 -> 100.03526 | C33: =((1/($B$30))^2)*D19*(1-D19)*(1.96)^2 -> 150.43706 | D33: =((1/($B$30))^2)*E19*(1-E19)*(1.96)^2 -> 72.9904
A35: current half-width for 95% CI | B35: targeted advertising | C35: profiling | D35: selling/sharing
A36: Advertising + FingerprintGen + Social | B36: =1.96*SQRT((C19)*(1-C19)/$B19) -> 0.050776259 | C36: =1.96*SQRT((D19)*(1-D19)/$B19) -> 0.062267517 | D36: =1.96*SQRT((E19)*(1-E19)/$B19) -> 0.043372755

Sheet Methodology
A1: Disconnect List accessed on: September 15, 2023
A3: Choosing the Websites to Analyze
A4: First we narrowed down the cateogries of sites we wanted to analyze to Advertising, Analytics, Fingerprinting General, Fingerprinting Invasive, and Social.
A5: Then we randomly generated individual numbers between 0 and the max amount of sites in each category.
A6: For Advertising we generated 76 numbers, Analytics had 30 numbers, and FingerprintGen, FingerprintInv and Social all had 15 numbers generated
A7: These random numbers corresponded to the listing of sites in the Disconnect list per category.
A9: Methodology Per Site:
A10: 1. Enter the Disconnect list and go to the cateogry. Then find the site which corresponds to the number that was generated
A11: 2. Copy and paste the URL from the Disconnect list into your browser
B12: a. If the URL is foreign without an English translation, or the domain is down, move to the next number after. Be sure to check that the new number has not already been analyzed and replace the ID when you find an analyzable site.
A15: 3. Scroll to the bottom of the website and click on 'Privacy Policy', or an equivalent link
A16: 4. To check for target advertising: First look for keywords such as 'targeted', 'personalized', 'customized'. If those don't show proof then look for sections that acknowledge what the site does with it's data. If still no proof, read through the policy looking for anything that would imply targeted advertising
A18: 5. To check for profiling: First look for keywords such as 'personal', 'identifiable', 'profiling'. If those don't show proof then look for sections that acknowledge how the site collects data and what it collects. If still no proof, read through the policy looking for anything that would imply profiling or collection Personally Identifiable Information.
A20: 6. To check for selling: First look for keywords such as 'sharing', 'selling', 'third party'. If those don't show proof then look for sections that acknowledge why the site collects data and what it does with it. If still no proof, read through the policy looking for anything that would imply profiling or collection Personally Identifiable Information.
A22: 7. If any valuable information is found it should be put into the spreadsheet under "Evidence" and the link for the site should be put into "Relevant URL."
A23: 8. To check for crosslisting: CTRL + F for the website URL in the Disconnect list
A25: Column Definitions
A26: Selling: Is a site "selling" information?
A27: Setting not to sell: Does this site have an option to prevent cross contextual share of information?
A28: Selling by default: Does the site start off collecting and "selling" information?
A29: Sign of not selling: If the site has an option to prevent cross contextual share of information, does it have a marker?

Sheet Twitter
A1: Network URL [URL] | B1: Date of Analysis [DATE] | C1: Reviewer [Name] | D1: Targeted Advertising [0, 1] | E1: Evidence | F1: Profiling [0, 1] | G1: Evidence | H1: Selling/ Sharing [0, 1] | I1: Evidence | J1: Setting: To Opt Out [0, 1] | K1: Evidence | L1: Selling By Default [0, 1] | M1: Evidence | N1: Sign of Not Selling [0, 1] | O1: What is it [Name of Tag] | P1: Evidence | Q1: Relevant URL [URL]
A2: https://twitter.com/ | B2: 45294 | C2: Kate | D2: 1 | E2: We also use the information we collect to improve and personalize our products and services so that you have a better experience on X, including by showing you more relevant content and ads, suggesting people and topics to follow, enabling and helping you discover affiliates, third-party apps, and services. | H2: 1 | I2: When you use other online products and services, they may share information about that usage with us. Our ad and business partners share information with us such as browser cookie IDs, X-generated identifiers, mobile device IDs, hashed user information like email addresses, demographic or interest data, and content viewed or actions taken on a website or app. Information shared by ad partners and affiliates or collected by X from the websites and apps of ad partners and affiliates may be combined with the other information you share with X and that X receives, generates, or infers about you described elsewhere in this Privacy Policy. | J2: 1 | K2: X adheres to the Digital Advertising Alliance Self-Regulatory Principles for Online Behavioral Advertising (also referred to as “interest-based advertising”) and respects the DAA’s consumer choice tool for you to opt out of interest-based advertising at https://optout.aboutads.info/. | L2: 1 | M2: Proof by existence of optout | N2: 0 | O2: unclear
